Workbook

Sheet Read Me
B2: NYOD — GTM & Weekly Forecast Model (Jul 2026 – Jun 2027)
B4: Built for: The NYOD GTM Challenge (₹2.5L → ₹1cr MRR in 12 months)
B6: HOW THIS WORKBOOK IS ORGANISED
B7: 1. Assumptions & Log — every driver, its Base/Bull/Bear value, and the rationale. Change the scenario switch (cell C3) to Base, Bull or Bear and the entire model recalculates.
B8: 2. Monthly Engine — the driver tree: spend → CAC → orders → repeat/subscription → revenue → cans → CM1/CM2 → EBITDA → cash, one column per month, fully formula-linked to Assumptions.
B9: 3. Weekly Rollout — 52 weekly rows (Jul 1, 2026 – Jun 29, 2027). Each week = its month's Monthly Engine total x a within-month weight (weights sum to 1, so weekly rows always tie back to the monthly engine exactly).
B10: 4. Monthly Rollup & Cash — the path to Rs 1cr MRR, capacity vs cans required, batch orders, and the running cash balance against the Rs 5L covenant floor.
B11: 5. Scenario Comparison — Base / Bull / Bear side-by-side (computed by running the engine under each scenario). Reference snapshot; recreate live by switching the toggle on the Assumptions tab.
B12: 6. Sensitivity — Month-12 revenue sensitivity to the 3 assumptions the outcome is most exposed to.
B14: KEY MODELLING CHOICES (see Assumptions & Log tab for full detail + rationale):
B15: - Weekly rows disaggregate monthly cohort/subscription dynamics evenly across the weeks of a month; only new-customer acquisition (paid+organic) carries week-specific nudges for named calendar events (Diwali week, New Year gut-health spike week).
B16: - 'MRR' = monthly net revenue run-rate, per the founders' usage (brief, Sec 9). Only Subscribe & Save is contractually recurring; this is called out wherever relevant.
... B18: - Blue text = hardcoded input/assumption. Black = formula. Green = cross-sheet link.

Sheet Assumptions & Log
A1: ASSUMPTIONS, SCENARIO SWITCH & ASSUMPTION LOG
A3: SCENARIO SWITCH: | B3: Base | C3: <- change this cell to Base / Bull / Bear. Everything downstream recalculates.
A5: Key | B5: Driver / Assumption | C5: Base | D5: Bull | E5: Bear | F5: Active | G5: Rationale | H5: Source / Basis
A6: cash0 | B6: Opening cash, Jul 1 2026 (₹) | C6: 3140000 | D6: 3140000 | E6: 3140000 | F6: =CHOOSE(MATCH($B$3,{"Base","Bull","Bear"},0),C6,D6,E6) -> 3140000 | G6: Founders' cash position at close of the data-pack period. | H6: Data pack: Financial Position, Jun 30 2026
A7: cac0 | B7: Opening blended paid CAC, Jul 2026 (₹) | C7: 536.5 | D7: 536.5 | E7: 536.5 | F7: =CHOOSE(MATCH($B$3,{"Base","Bull","Bear"},0),C7,D7,E7) -> 536.5 | G7: June actual blended paid CAC (Meta+Google spend ÷ Meta+Google last-click orders). | H7: Data pack: Channel Performance, June 2026
A8: cum_cust0 | B8: Cumulative D2C customers as of Jun 30, 2026 | C8: 488 | D8: 488 | E8: 488 | F8: =CHOOSE(MATCH($B$3,{"Base","Bull","Bear"},0),C8,D8,E8) -> 488 | G8: May cohort (223) + June new customers (265). | H8: Data pack: Retention & Subs
A9: subs0 | B9: Active subscribers, Jun 30 2026 | C9: 47 | D9: 47 | E9: 47 | F9: =CHOOSE(MATCH($B$3,{"Base","Bull","Bear"},0),C9,D9,E9) -> 47 | G9: Given directly. | H9: Data pack: Retention & Subs
A10: capacity0 | B10: Starting capacity ceiling (cans/month) | C10: 48000 | D10: 48000 | E10: 48000 | F10: =CHOOSE(MATCH($B$3,{"Base","Bull","Bear"},0),C10,D10,E10) -> 48000 | G10: Co-packer MOQ 24,000/batch x 2 batches/month max on current line. | H10: Founder Notes #10
A12: paid_spend0 | B12: Opening monthly paid spend, Jul-26 (₹) | C12: 115000 | D12: 135000 | E12: 100000 | F12: =CHOOSE(MATCH($B$3,{"Base","Bull","Bear"},0),C12,D12,E12) -> 115000 | G12: Base holds spend growth close to June's trajectory; Bull front-loads spend assuming a Q3 funding top-up is likely; Bear assumes founders get cautious after a weak July.
A13: paid_g_hi | B13: Monthly paid-spend growth, high-demand months | C13: 0.16 | D13: 0.21 | E13: 0.07 | F13: =CHOOSE(MATCH($B$3,{"Base","Bull","Bear"},0),C13,D13,E13) -> 0.16 | G13: Applied in months where the seasonality index >= June-2026 reference (festive/summer). Bull pushes harder into tailwind months; Bear conserves cash. | H13: Derived: May->Jun Meta+Google spend grew +47% WoW-ish during scale-up; tapered down for realism post fund-constrained periods.
A14: paid_g_lo | B14: Monthly paid-spend growth, low-demand months | C14: 0.05 | D14: 0.09 | E14: 0.01 | F14: =CHOOSE(MATCH($B$3,{"Base","Bull","Bear"},0),C14,D14,E14) -> 0.05 | G14: Applied Jul-Sep monsoon and Dec-Feb winter troughs — spend still grows (new creative, retargeting) but far slower than peak season.
A15: cac_drift | B15: Structural monthly CAC inflation (pre-relief) | C15: 0.014 | D15: 0.012 | E15: 0.026 | F15: =CHOOSE(MATCH($B$3,{"Base","Bull","Bear"},0),C15,D15,E15) -> 0.014 | G15: Reflects rising CPMs/frequency on a single-creative Meta account (May->Jun CAC actually rose from ₹448->536, +19.7% in one month) and increasing competitive intensity in the RTD/functional-drinks category. | H15: Data pack: Channel Performance MoM CAC; Founder Notes #8 (CPM +22%, frequency 3.8)
A16: cac_relief_m | B16: Month index (0=Jul-26) when creative-refresh programme lands | C16: 3 | D16: 2 | E16: 6 | F16: =CHOOSE(MATCH($B$3,{"Base","Bull","Bear"},0),C16,D16,E16) -> 3 | G16: A dedicated content/creative hire (see hiring plan) is assumed to break the single-creative fatigue loop. Bull hires faster; Bear delays because of cash stress.
A17: cac_relief | B17: Structural monthly CAC inflation, post-relief | C17: 0.005 | D17: 0.006 | E17: 0.004 | F17: =CHOOSE(MATCH($B$3,{"Base","Bull","Bear"},0),C17,D17,E17) -> 0.005 | G17: Even with more creative throughput, category CPCs keep rising as more D2C brands enter; relief only partially offsets drift.
A18: referral_rate | B18: Monthly organic referrals as % of cumulative customer base | C18: 0.028 | D18: 0.045 | E18: 0.012 | F18: =CHOOSE(MATCH($B$3,{"Base","Bull","Bear"},0),C18,D18,E18) -> 0.028 | G18: Organic (non-paid, non-content) orders = referral_rate x cumulative customers, i.e. a WOM/network effect that compounds as the customer base grows. Calibrated so June's actual organic share (103 of 303 orders, ~34%) is the starting order of magnitude, then let it compound. | H18: Data pack: Channel Performance (Organic+Direct+SEO+CRM = 103 of 303 June orders)
A19: content_baseline | B19: Baseline monthly organic/content orders (demand-adjusted) | C19: 25 | D19: 40 | E19: 10 | F19: =CHOOSE(MATCH($B$3,{"Base","Bull","Bear"},0),C19,D19,E19) -> 25 | G19: SEO, content and CRM-driven orders that don't scale off the referral network effect — floor demand independent of paid spend.
A20: repeat_prob_start | B20: Monthly repeat-purchase probability, Jul-26 | C20: 0.16 | D20: 0.17 | E20: 0.11 | F20: =CHOOSE(MATCH($B$3,{"Base","Bull","Bear"},0),C20,D20,E20) -> 0.16 | G20: Applied to the pool of customers acquired 1-2 months prior (D2C repeat cohort, excluding subscribers). May-cohort actuals show 15.2% repurchased within ~45 days — used as the anchor. | H20: Data pack: Retention & Subs (May cohort, 15.2% repurchase by Jun 30, avg 26 days to 2nd order)
A21: repeat_prob_end | B21: Monthly repeat-purchase probability, Jun-27 | C21: 0.24 | D21: 0.3 | E21: 0.15 | F21: =CHOOSE(MATCH($B$3,{"Base","Bull","Bear"},0),C21,D21,E21) -> 0.24 | G21: Assumes lifecycle email/WhatsApp flows, loyalty perks and better PDP trust signals lift repeat behaviour over 12 months — a common D2C trajectory as retention programmes mature.
A22: sub_share_start | B22: Share of new customers opting into Subscribe&Save, Jul-26 | C22: 0.09 | D22: 0.1 | E22: 0.07 | F22: =CHOOSE(MATCH($B$3,{"Base","Bull","Bear"},0),C22,D22,E22) -> 0.09 | G22: June actual was already 8% of orders within 3 weeks of launch (Jun 10). Assume slight uptick as it becomes a default checkout nudge. | H22: Data pack: Retention & Subs (8% of June orders)
A23: sub_share_end | B23: Share of new customers opting into Subscribe&Save, Jun-27 | C23: 0.24 | D23: 0.32 | E23: 0.13 | F23: =CHOOSE(MATCH($B$3,{"Base","Bull","Bear"},0),C23,D23,E23) -> 0.24 | G23: Assumes active pack-architecture/pricing nudges toward subscription (10% discount + convenience) become a core PLG lever.
A24: sub_renewal | B24: Monthly subscription renewal rate | C24: 0.8 | D24: 0.84 | E24: 0.66 | F24: =CHOOSE(MATCH($B$3,{"Base","Bull","Bear"},0),C24,D24,E24) -> 0.8 | G24: No renewal data exists yet (first renewals due Jul 10). Benchmarked to typical D2C subscribe&save monthly renewal of 70-85%; Bear assumes renewal disappoints badly. | H24: Assumption — flagged as unknown in data pack (Retention & Subs: 'renewal rate unknown — you must assume one')
A25: aov_drift | B25: Monthly AOV growth (price + pack-mix upsize) | C25: 0.011 | D25: 0.016 | E25: 0.004 | F25: =CHOOSE(MATCH($B$3,{"Base","Bull","Bear"},0),C25,D25,E25) -> 0.011 | G25: Combines a modest price increase (allowed per brief Sec.4, pack/pricing changes permitted with justification) with mix-shift toward 12-packs/Subscribe (already the repeat-buyer pattern per Retention & Subs). | H25: Data pack: Retention & Subs ('repeat customers upsize to 12-packs')
A26: mkt_launch | B26: Month index Amazon marketplace goes live | C26: 1 | D26: 1 | E26: 2 | F26: =CHOOSE(MATCH($B$3,{"Base","Bull","Bear"},0),C26,D26,E26) -> 1 | G26: Beverage-compliance + FBA onboarding takes ~4 weeks per the founders' consultant; decision made in Jul, live by Aug (Base/Bull) or Sep (Bear, if deprioritised). | H26: Founder Notes #2 (not listed on Amazon; ~4-week onboarding)
A27: mkt_aov | B27: Marketplace (Amazon) AOV, ₹ | C27: 680 | D27: 700 | E27: 650 | F27: =CHOOSE(MATCH($B$3,{"Base","Bull","Bear"},0),C27,D27,E27) -> 680 | G27: Marketplace baskets skew smaller than D2C site baskets (single mid-pack SKU behaviour is typical on marketplaces).
A28: mkt_take | B28: Marketplace referral/fee take-rate | C28: 0.15 | D28: 0.15 | E28: 0.15 | F28: =CHOOSE(MATCH($B$3,{"Base","Bull","Bear"},0),C28,D28,E28) -> 0.15 | G28: Approximate Amazon beverage-category referral fee. | H28: Category benchmark (Amazon India seller fee schedule, beverages ~15%)
A29: mkt_add | B29: Marketplace monthly order-growth increment | C29: 110 | D29: 170 | E29: 40 | F29: =CHOOSE(MATCH($B$3,{"Base","Bull","Bear"},0),C29,D29,E29) -> 110 | G29: Additive new marketplace orders/month once live, scaled by the seasonality index.
A30: qc_launch | B30: Month index Quick-Commerce (Blinkit) pilot goes live | C30: 2 | D30: 1 | E30: 99 | F30: =CHOOSE(MATCH($B$3,{"Base","Bull","Bear"},0),C30,D30,E30) -> 2 | G30: Blinkit's inbound (2-city pilot, Jun 24) is accepted in Base/Bull after a short negotiation on trade terms; Bear assumes NYOD declines/delays the pilot to conserve cash and management bandwidth. | H30: Founder Notes #1 (Blinkit inbound: 18-22% trade margin, ~₹2L upfront, fortnightly replenishment)
A31: qc_aov | B31: Quick-commerce basket AOV, ₹ | C31: 520 | D31: 540 | E31: 500 | F31: =CHOOSE(MATCH($B$3,{"Base","Bull","Bear"},0),C31,D31,E31) -> 520 | G31: Quick-commerce baskets are impulse-sized — smaller than D2C or even marketplace.
A32: qc_take | B32: Quick-commerce trade margin to platform | C32: 0.2 | D32: 0.2 | E32: 0.2 | F32: =CHOOSE(MATCH($B$3,{"Base","Bull","Bear"},0),C32,D32,E32) -> 0.2 | G32: Midpoint of the Blinkit-quoted 18-22% trade margin range. | H32: Founder Notes #1
A33: qc_add | B33: Quick-commerce monthly order-growth increment | C33: 90 | D33: 160 | E33: 0 | F33: =CHOOSE(MATCH($B$3,{"Base","Bull","Bear"},0),C33,D33,E33) -> 90 | G33: Additive QC orders/month once live (2-city pilot: Delhi NCR + Bangalore, NYOD's #1 and #2 metros by order share). | H33: Founder Notes #7 (Delhi NCR 28%, Bangalore 19% of orders)
A34: exp2_m | B34: Month index capacity expansion #2 is COMMITTED | C34: 1 | D34: 0 | E34: 99 | F34: =CHOOSE(MATCH($B$3,{"Base","Bull","Bear"},0),C34,D34,E34) -> 1 | G34: A 2nd co-packer line (~₹6L capex, 60-75 day lead) is ordered in Aug-26 (Base) or immediately in Jul-26 (Bull) to be ready ahead of the Oct-Nov festive peak. Bear never commits — demand never requires it. | H34: Founder Notes #10 (2nd line: 60-75 days, ~₹6L)
A35: exp2_lead | B35: Lead time for expansion #2 (months, rounded) | C35: 2 | D35: 2 | E35: 3 | F35: =CHOOSE(MATCH($B$3,{"Base","Bull","Bear"},0),C35,D35,E35) -> 2 | G35: 60-75 days ≈ 2-2.5 months; Bear assumes a slower vendor process given lower urgency.
A36: exp3_m | B36: Month index capacity expansion #3 is COMMITTED (99=never) | C36: 7 | D36: 5 | E36: 99 | F36: =CHOOSE(MATCH($B$3,{"Base","Bull","Bear"},0),C36,D36,E36) -> 7 | G36: A 3rd line/co-packer is only committed in Bull, once Q2 festive results and Bull-case funding (see raise) de-risk the capex.
A37: exp3_lead | B37: Lead time for expansion #3 (months) | C37: 3 | D37: 3 | E37: 3 | F37: =CHOOSE(MATCH($B$3,{"Base","Bull","Bear"},0),C37,D37,E37) -> 3
A39: OPERATING & COST ASSUMPTIONS (same across scenarios unless noted)
A40: Key | B40: Driver / Assumption | C40: Base | D40: Bull | E40: Bear | F40: Active | G40: Rationale | H40: Source / Basis
A41: cogs_can_start | B41: COGS per can, Jul-26 (₹) | C41: 52 | D41: 52 | E41: 52 | F41: =CHOOSE(MATCH($B$3,{"Base","Bull","Bear"},0),C41,D41,E41) -> 52 | G41: Unchanged from June actual (₹28 ingredients + ₹16 can/label + ₹8 co-packer fee). | H41: Data pack: Monthly P&L unit-economics inputs
A42: cogs_can_end | B42: COGS per can, Jun-27 (₹) | C42: 47 | D42: 45 | E42: 50 | F42: =CHOOSE(MATCH($B$3,{"Base","Bull","Bear"},0),C42,D42,E42) -> 47 | G42: Modest volume-driven co-packer renegotiation as batch volumes scale; Bear assumes no leverage since volumes stay low.
A43: ship_ord_start | B43: Shipping per order, Jul-26 (₹) | C43: 76 | D43: 76 | E43: 76 | F43: =CHOOSE(MATCH($B$3,{"Base","Bull","Bear"},0),C43,D43,E43) -> 76 | G43: June actual. | H43: Data pack: Monthly P&L unit-economics inputs
A44: ship_ord_end | B44: Shipping per order, Jun-27 (₹) | C44: 64 | D44: 60 | E44: 72 | F44: =CHOOSE(MATCH($B$3,{"Base","Bull","Bear"},0),C44,D44,E44) -> 64 | G44: Freight consolidation / carrier renegotiation at higher volumes.
A45: gateway_pct | B45: Payment gateway fee, % of net revenue | C45: 0.02 | D45: 0.02 | E45: 0.02 | F45: =CHOOSE(MATCH($B$3,{"Base","Bull","Bear"},0),C45,D45,E45) -> 0.02 | G45: Unchanged from data pack. | H45: Data pack: Monthly P&L
A46: box_cost | B46: Boxes & packaging per D2C order (₹) | C46: 22 | D46: 22 | E46: 22 | F46: =CHOOSE(MATCH($B$3,{"Base","Bull","Bear"},0),C46,D46,E46) -> 22 | G46: Unchanged from data pack (applied to D2C orders only; marketplace/QC use platform-standard packaging, already reflected in the lower take-home AOV). | H46: Data pack: Monthly P&L
A47: wc_drag_pct | B47: Working-capital drag, % of monthly COGS | C47: 0.15 | D47: 0.15 | E47: 0.15 | F47: =CHOOSE(MATCH($B$3,{"Base","Bull","Bear"},0),C47,D47,E47) -> 0.15 | G47: Proxy for the cash-timing mismatch created by the co-packer's 50% advance-on-order / 50% on-dispatch terms versus D2C cash-upfront receipts. | H47: Founder Notes #10, #11
A48: capex_per_exp | B48: Capex per capacity expansion (₹) | C48: 600000 | D48: 600000 | E48: 600000 | F48: =CHOOSE(MATCH($B$3,{"Base","Bull","Bear"},0),C48,D48,E48) -> 600000 | G48: 2nd/3rd co-packer line onboarding cost. | H48: Founder Notes #10
A49: hire1_month | B49: Month index of Hire 1 (growth/creative associate) | C49: 2 | D49: 1 | E49: 4 | F49: =CHOOSE(MATCH($B$3,{"Base","Bull","Bear"},0),C49,D49,E49) -> 2 | G49: A dedicated content/performance hire to break Meta creative fatigue (see cac_relief_m).
A50: hire1_amt | B50: Hire 1 monthly fully-loaded cost (₹) | C50: 40000 | D50: 40000 | E50: 35000 | F50: =CHOOSE(MATCH($B$3,{"Base","Bull","Bear"},0),C50,D50,E50) -> 40000
A51: hire2_month | B51: Month index of Hire 2 (ops/supply chain exec) | C51: 5 | D51: 3 | E51: 99 | F51: =CHOOSE(MATCH($B$3,{"Base","Bull","Bear"},0),C51,D51,E51) -> 5 | G51: Brought on as 2nd capacity line and multi-channel fulfilment (marketplace+QC) add ops complexity.
A52: hire2_amt | B52: Hire 2 monthly fully-loaded cost (₹) | C52: 35000 | D52: 35000 | E52: 0 | F52: =CHOOSE(MATCH($B$3,{"Base","Bull","Bear"},0),C52,D52,E52) -> 35000
A53: hire3_month | B53: Month index of Hire 3 (category/marketplace manager) | C53: 8 | D53: 5 | E53: 99 | F53: =CHOOSE(MATCH($B$3,{"Base","Bull","Bear"},0),C53,D53,E53) -> 8 | G53: Added once marketplace + quick-commerce scale enough to need dedicated management.
A54: hire3_amt | B54: Hire 3 monthly fully-loaded cost (₹) | C54: 40000 | D54: 45000 | E54: 0 | F54: =CHOOSE(MATCH($B$3,{"Base","Bull","Bear"},0),C54,D54,E54) -> 40000
A55: raise_month | B55: Month index of funding raise (99=none) | C55: 99 | D55: 6 | E55: 99 | F55: =CHOOSE(MATCH($B$3,{"Base","Bull","Bear"},0),C55,D55,E55) -> 99 | G55: Base plans to reach ₹1cr organically off existing cash; Bull assumes a ~₹1.8cr top-up around Jan-27, justified by 6 months of festive-season traction, positive CM2 by Q2 and de-risked marketplace/QC unit economics — used to fund a 3rd capacity line + national QC rollout. Bear never raises. | H55: Rubric Sec.4: 'bull case may include a raise — state amount, timing, milestones'
A56: raise_amount | B56: Funding raise amount (₹) | C56: 0 | D56: 18000000 | E56: 0 | F56: =CHOOSE(MATCH($B$3,{"Base","Bull","Bear"},0),C56,D56,E56) -> 0
A57: cash_floor | B57: Minimum cash covenant (₹) | C57: 500000 | D57: 500000 | E57: 500000 | F57: =CHOOSE(MATCH($B$3,{"Base","Bull","Bear"},0),C57,D57,E57) -> 500000 | G57: Per brief Sec.4 — base case cash may never fall below ₹5L. | H57: Brief Sec.4

Sheet Monthly Engine
B1: MONTHLY DRIVER ENGINE (fully linked to Assumptions & Log — switch scenario there)
B3: Month index (0 = Jul-26) | C3: 0 | D3: 1 | E3: 2 | F3: 3 | G3: 4 | H3: 5 | I3: 6 | J3: 7 | K3: 8 | L3: 9 | M3: 10 | N3: 11
B4: Month | C4: Jul-26 | D4: Aug-26 | E4: Sep-26 | F4: Oct-26 | G4: Nov-26 | H4: Dec-26 | I4: Jan-27 | J4: Feb-27 | K4: Mar-27 | L4: Apr-27 | M4: May-27 | N4: Jun-27
B5: RTD/functional-beverage demand index | C5: 96 | D5: 88 | E5: 92 | F5: 108 | G5: 104 | H5: 84 | I5: 78 | J5: 82 | K5: 98 | L5: 122 | M5: 132 | N5: 128
B6: Gut-health interest index | C6: 94 | D6: 92 | E6: 96 | F6: 98 | G6: 96 | H6: 94 | I6: 126 | J6: 108 | K6: 100 | L6: 102 | M6: 98 | N6: 96
B7: Demand multiplier (vs Jun-26 baseline) | C7: =(0.75*C5+0.25*C6)/(0.75*128+0.25*96) -> 0.79583333 | D7: =(0.75*D5+0.25*D6)/(0.75*128+0.25*96) -> 0.74166667 | E7: =(0.75*E5+0.25*E6)/(0.75*128+0.25*96) -> 0.775 | F7: =(0.75*F5+0.25*F6)/(0.75*128+0.25*96) -> 0.87916667 | G7: =(0.75*G5+0.25*G6)/(0.75*128+0.25*96) -> 0.85 | H7: =(0.75*H5+0.25*H6)/(0.75*128+0.25*96) -> 0.72083333 | I7: =(0.75*I5+0.25*I6)/(0.75*128+0.25*96) -> 0.75 | J7: =(0.75*J5+0.25*J6)/(0.75*128+0.25*96) -> 0.7375 | ... N7: =(0.75*N5+0.25*N6)/(0.75*128+0.25*96) -> 1
B9: ACQUISITION & CAC
B10: Paid media spend (Meta+Google), ₹ | C10: ='Assumptions & Log'!$F$12 -> 115000 | D10: =C10*(1+IF(D7>=1,'Assumptions & Log'!$F$13,'Assumptions & Log'!$F$14))*IF(C67<'Assumptions & Log'!$F$57,0.85,1) -> 120750 | E10: =D10*(1+IF(E7>=1,'Assumptions & Log'!$F$13,'Assumptions & Log'!$F$14))*IF(D67<'Assumptions & Log'!$F$57,0.85,1) -> 126787.5 | F10: =E10*(1+IF(F7>=1,'Assumptions & Log'!$F$13,'Assumptions & Log'!$F$14))*IF(E67<'Assumptions & Log'!$F$57,0.85,1) -> 133126.88 | G10: =F10*(1+IF(G7>=1,'Assumptions & Log'!$F$13,'Assumptions & Log'!$F$14))*IF(F67<'Assumptions & Log'!$F$57,0.85,1) -> 139783.22 | H10: =G10*(1+IF(H7>=1,'Assumptions & Log'!$F$13,'Assumptions & Log'!$F$14))*IF(G67<'Assumptions & Log'!$F$57,0.85,1) -> 146772.38 | I10: =H10*(1+IF(I7>=1,'Assumptions & Log'!$F$13,'Assumptions & Log'!$F$14))*IF(H67<'Assumptions & Log'!$F$57,0.85,1) -> 154111 | J10: =I10*(1+IF(J7>=1,'Assumptions & Log'!$F$13,'Assumptions & Log'!$F$14))*IF(I67<'Assumptions & Log'!$F$57,0.85,1) -> 161816.55 | K10: =J10*(1+IF(K7>=1,'Assumptions & Log'!$F$13,'Assumptions & Log'!$F$14))*IF(J67<'Assumptions & Log'!$F$57,0.85,1) -> 169907.38 | ... N10: =M10*(1+IF(N7>=1,'Assumptions & Log'!$F$13,'Assumptions & Log'!$F$14))*IF(M67<'Assumptions & Log'!$F$57,0.85,1) -> 240058.73
B11: CAC structural trend (pre-seasonality), ₹ | C11: ='Assumptions & Log'!$F$7 -> 536.5 | D11: =C11*(1+IF(D3<'Assumptions & Log'!$F$16,'Assumptions & Log'!$F$15,'Assumptions & Log'!$F$17)) -> 544.011 | E11: =D11*(1+IF(E3<'Assumptions & Log'!$F$16,'Assumptions & Log'!$F$15,'Assumptions & Log'!$F$17)) -> 551.62715 | F11: =E11*(1+IF(F3<'Assumptions & Log'!$F$16,'Assumptions & Log'!$F$15,'Assumptions & Log'!$F$17)) -> 554.38529 | G11: =F11*(1+IF(G3<'Assumptions & Log'!$F$16,'Assumptions & Log'!$F$15,'Assumptions & Log'!$F$17)) -> 557.15722 | H11: =G11*(1+IF(H3<'Assumptions & Log'!$F$16,'Assumptions & Log'!$F$15,'Assumptions & Log'!$F$17)) -> 559.943 | I11: =H11*(1+IF(I3<'Assumptions & Log'!$F$16,'Assumptions & Log'!$F$15,'Assumptions & Log'!$F$17)) -> 562.74272 | J11: =I11*(1+IF(J3<'Assumptions & Log'!$F$16,'Assumptions & Log'!$F$15,'Assumptions & Log'!$F$17)) -> 565.55643 | K11: =J11*(1+IF(K3<'Assumptions & Log'!$F$16,'Assumptions & Log'!$F$15,'Assumptions & Log'!$F$17)) -> 568.38421 | ... N11: =M11*(1+IF(N3<'Assumptions & Log'!$F$16,'Assumptions & Log'!$F$15,'Assumptions & Log'!$F$17)) -> 576.95268
B12: Blended paid CAC — seasonality-adjusted, ₹ | C12: =MAX(C11/C7,300) -> 674.13613 | D12: =MAX(D11/D7,300) -> 733.49798 | E12: =MAX(E11/E7,300) -> 711.77697 | F12: =MAX(F11/F7,300) -> 630.58042 | G12: =MAX(G11/G7,300) -> 655.47908 | H12: =MAX(H11/H7,300) -> 776.79954 | I12: =MAX(I11/I7,300) -> 750.32362 | J12: =MAX(J11/J7,300) -> 766.85618 | ... N12: =MAX(N11/N7,300) -> 576.95268
B13: New customers — paid | C13: =C10/C12 -> 170.58869 | D13: =D10/D12 -> 164.62213 | E13: =E10/E12 -> 178.12813 | F13: =F10/F12 -> 211.118 | G13: =G10/G12 -> 213.25352 | H13: =H10/H12 -> 188.94499 | I13: =I10/I12 -> 205.39271 | J13: =J10/J12 -> 211.0129 | ... N13: =N10/N12 -> 416.08046
B14: New customers — organic/referral | C14: ='Assumptions & Log'!$F$18*'Assumptions & Log'!$F$8+'Assumptions & Log'!$F$19*C7 -> 33.559833 | D14: ='Assumptions & Log'!$F$18*C16+'Assumptions & Log'!$F$19*D7 -> 37.921825 | E14: ='Assumptions & Log'!$F$18*D16+'Assumptions & Log'!$F$19*E7 -> 44.426389 | F14: ='Assumptions & Log'!$F$18*E16+'Assumptions & Log'!$F$19*F7 -> 53.262083 | G14: ='Assumptions & Log'!$F$18*F16+'Assumptions & Log'!$F$19*G7 -> 59.935558 | H14: ='Assumptions & Log'!$F$18*G16+'Assumptions & Log'!$F$19*H7 -> 64.355686 | I14: ='Assumptions & Log'!$F$18*H16+'Assumptions & Log'!$F$19*I7 -> 72.177271 | J14: ='Assumptions & Log'!$F$18*I16+'Assumptions & Log'!$F$19*J7 -> 79.63673 | K14: ='Assumptions & Log'!$F$18*J16+'Assumptions & Log'!$F$19*K7 -> 89.858254 | ... N14: ='Assumptions & Log'!$F$18*M16+'Assumptions & Log'!$F$19*N7 -> 128.76903
B15: New first-time customers (total) | C15: =C13+C14 -> 204.14853 | D15: =D13+D14 -> 202.54396 | E15: =E13+E14 -> 222.55452 | F15: =F13+F14 -> 264.38008 | G15: =G13+G14 -> 273.18908 | H15: =H13+H14 -> 253.30067 | I15: =I13+I14 -> 277.56998 | J15: =J13+J14 -> 290.64963 | ... N15: =N13+N14 -> 544.84949
B16: Cumulative D2C customers (end of month) | C16: ='Assumptions & Log'!$F$8+C15 -> 692.14853 | D16: =C16+D15 -> 894.69248 | E16: =D16+E15 -> 1117.247 | F16: =E16+F15 -> 1381.6271 | G16: =F16+G15 -> 1654.8162 | H16: =G16+H15 -> 1908.1168 | I16: =H16+I15 -> 2185.6868 | J16: =I16+J15 -> 2476.3364 | K16: =J16+K15 -> 2811.5668 | ... N16: =M16+N15 -> 4250.8863
B18: RETENTION & SUBSCRIPTION
B19: Repeat-eligible pool (customers acquired 1-2 mo ago) | C19: =0 -> 0 | D19: =C15 -> 204.14853 | E19: =SUM(C15:D15) -> 406.69248 | F19: =SUM(D15:E15) -> 425.09847 | G19: =SUM(E15:F15) -> 486.9346 | H19: =SUM(F15:G15) -> 537.56915 | I19: =SUM(G15:H15) -> 526.48975 | J19: =SUM(H15:I15) -> 530.87065 | K19: =SUM(I15:J15) -> 568.21961 | L19: =SUM(J15:K15) -> 625.88 | ... N19: =SUM(L15:M15) -> 894.47005
B20: Monthly repeat-purchase probability | C20: ='Assumptions & Log'!$F$20+('Assumptions & Log'!$F$21-'Assumptions & Log'!$F$20)*C3/11 -> 0.16 | D20: ='Assumptions & Log'!$F$20+('Assumptions & Log'!$F$21-'Assumptions & Log'!$F$20)*D3/11 -> 0.16727273 | E20: ='Assumptions & Log'!$F$20+('Assumptions & Log'!$F$21-'Assumptions & Log'!$F$20)*E3/11 -> 0.17454545 | F20: ='Assumptions & Log'!$F$20+('Assumptions & Log'!$F$21-'Assumptions & Log'!$F$20)*F3/11 -> 0.18181818 | G20: ='Assumptions & Log'!$F$20+('Assumptions & Log'!$F$21-'Assumptions & Log'!$F$20)*G3/11 -> 0.18909091 | H20: ='Assumptions & Log'!$F$20+('Assumptions & Log'!$F$21-'Assumptions & Log'!$F$20)*H3/11 -> 0.19636364 | I20: ='Assumptions & Log'!$F$20+('Assumptions & Log'!$F$21-'Assumptions & Log'!$F$20)*I3/11 -> 0.20363636 | J20: ='Assumptions & Log'!$F$20+('Assumptions & Log'!$F$21-'Assumptions & Log'!$F$20)*J3/11 -> 0.21090909 | ... N20: ='Assumptions & Log'!$F$20+('Assumptions & Log'!$F$21-'Assumptions & Log'!$F$20)*N3/11 -> 0.24
B21: Repeat orders | C21: =C19*C20 -> 0 | D21: =D19*D20 -> 34.148481 | E21: =E19*E20 -> 70.986324 | F21: =F19*F20 -> 77.290632 | G21: =G19*G20 -> 92.074905 | H21: =H19*H20 -> 105.55903 | I21: =I19*I20 -> 107.21246 | J21: =J19*J20 -> 111.96545 | ... N21: =N19*N20 -> 214.67281
B22: Share of new customers -> Subscribe&Save | C22: ='Assumptions & Log'!$F$22+('Assumptions & Log'!$F$23-'Assumptions & Log'!$F$22)*C3/11 -> 0.09 | D22: ='Assumptions & Log'!$F$22+('Assumptions & Log'!$F$23-'Assumptions & Log'!$F$22)*D3/11 -> 0.10363636 | E22: ='Assumptions & Log'!$F$22+('Assumptions & Log'!$F$23-'Assumptions & Log'!$F$22)*E3/11 -> 0.11727273 | F22: ='Assumptions & Log'!$F$22+('Assumptions & Log'!$F$23-'Assumptions & Log'!$F$22)*F3/11 -> 0.13090909 | G22: ='Assumptions & Log'!$F$22+('Assumptions & Log'!$F$23-'Assumptions & Log'!$F$22)*G3/11 -> 0.14454545 | H22: ='Assumptions & Log'!$F$22+('Assumptions & Log'!$F$23-'Assumptions & Log'!$F$22)*H3/11 -> 0.15818182 | I22: ='Assumptions & Log'!$F$22+('Assumptions & Log'!$F$23-'Assumptions & Log'!$F$22)*I3/11 -> 0.17181818 | J22: ='Assumptions & Log'!$F$22+('Assumptions & Log'!$F$23-'Assumptions & Log'!$F$22)*J3/11 -> 0.18545455 | ... N22: ='Assumptions & Log'!$F$22+('Assumptions & Log'!$F$23-'Assumptions & Log'!$F$22)*N3/11 -> 0.24
B23: New subscribers | C23: =C15*C22 -> 18.373367 | D23: =D15*D22 -> 20.990919 | E23: =E15*E22 -> 26.099575 | F23: =F15*F22 -> 34.609756 | G23: =G15*G22 -> 39.488239 | H23: =H15*H22 -> 40.067561 | I23: =I15*I22 -> 47.691569 | J23: =J15*J22 -> 53.902296 | ... N23: =N15*N22 -> 130.76388
B24: Active subscribers (end of month) | C24: ='Assumptions & Log'!$F$9*'Assumptions & Log'!$F$24+C23 -> 55.973367 | D24: =C24*'Assumptions & Log'!$F$24+D23 -> 65.769613 | E24: =D24*'Assumptions & Log'!$F$24+E23 -> 78.715266 | F24: =E24*'Assumptions & Log'!$F$24+F23 -> 97.581968 | G24: =F24*'Assumptions & Log'!$F$24+G23 -> 117.55381 | H24: =G24*'Assumptions & Log'!$F$24+H23 -> 134.11061 | I24: =H24*'Assumptions & Log'!$F$24+I23 -> 154.98006 | J24: =I24*'Assumptions & Log'!$F$24+J23 -> 177.88634 | K24: =J24*'Assumptions & Log'!$F$24+K23 -> 209.05039 | ... N24: =M24*'Assumptions & Log'!$F$24+N23 -> 381.45802
B25: Subscription orders | C25: =C24 -> 55.973367 | D25: =D24 -> 65.769613 | E25: =E24 -> 78.715266 | F25: =F24 -> 97.581968 | G25: =G24 -> 117.55381 | H25: =H24 -> 134.11061 | I25: =I24 -> 154.98006 | J25: =J24 -> 177.88634 | ... N25: =N24 -> 381.45802
B27: REVENUE
B28: D2C orders (first + repeat + subscription) | C28: =C15+C21+C25 -> 260.12189 | D28: =D15+D21+D25 -> 302.46205 | E28: =E15+E21+E25 -> 372.25611 | F28: =F15+F21+F25 -> 439.25268 | G28: =G15+G21+G25 -> 482.81779 | H28: =H15+H21+H25 -> 492.97032 | I28: =I15+I21+I25 -> 539.76249 | J28: =J15+J21+J25 -> 580.50142 | ... N28: =N15+N21+N25 -> 1140.9803
B29: D2C AOV, ₹ | C29: =829*(1+'Assumptions & Log'!$F$25)^C3 -> 829 | D29: =829*(1+'Assumptions & Log'!$F$25)^D3 -> 838.119 | E29: =829*(1+'Assumptions & Log'!$F$25)^E3 -> 847.33831 | F29: =829*(1+'Assumptions & Log'!$F$25)^F3 -> 856.65903 | G29: =829*(1+'Assumptions & Log'!$F$25)^G3 -> 866.08228 | H29: =829*(1+'Assumptions & Log'!$F$25)^H3 -> 875.60918 | I29: =829*(1+'Assumptions & Log'!$F$25)^I3 -> 885.24089 | J29: =829*(1+'Assumptions & Log'!$F$25)^J3 -> 894.97854 | ... N29: =829*(1+'Assumptions & Log'!$F$25)^N3 -> 935.01212
B30: D2C revenue, ₹ | C30: =C28*C29 -> 215641.05 | D30: =D28*D29 -> 253499.19 | E30: =E28*E29 -> 315426.86 | F30: =F28*F29 -> 376289.77 | G30: =G28*G29 -> 418159.94 | H30: =H28*H29 -> 431649.34 | I30: =I28*I29 -> 477819.83 | J30: =J28*J29 -> 519536.31 | ... N30: =N28*N29 -> 1066830.4
B31: Marketplace (Amazon) orders | C31: =IF(C3>='Assumptions & Log'!$F$26,'Assumptions & Log'!$F$29*(C3-'Assumptions & Log'!$F$26+1)*C7,0) -> 0 | D31: =IF(D3>='Assumptions & Log'!$F$26,'Assumptions & Log'!$F$29*(D3-'Assumptions & Log'!$F$26+1)*D7,0) -> 81.583333 | E31: =IF(E3>='Assumptions & Log'!$F$26,'Assumptions & Log'!$F$29*(E3-'Assumptions & Log'!$F$26+1)*E7,0) -> 170.5 | F31: =IF(F3>='Assumptions & Log'!$F$26,'Assumptions & Log'!$F$29*(F3-'Assumptions & Log'!$F$26+1)*F7,0) -> 290.125 | G31: =IF(G3>='Assumptions & Log'!$F$26,'Assumptions & Log'!$F$29*(G3-'Assumptions & Log'!$F$26+1)*G7,0) -> 374 | H31: =IF(H3>='Assumptions & Log'!$F$26,'Assumptions & Log'!$F$29*(H3-'Assumptions & Log'!$F$26+1)*H7,0) -> 396.45833 | I31: =IF(I3>='Assumptions & Log'!$F$26,'Assumptions & Log'!$F$29*(I3-'Assumptions & Log'!$F$26+1)*I7,0) -> 495 | J31: =IF(J3>='Assumptions & Log'!$F$26,'Assumptions & Log'!$F$29*(J3-'Assumptions & Log'!$F$26+1)*J7,0) -> 567.875 | ... N31: =IF(N3>='Assumptions & Log'!$F$26,'Assumptions & Log'!$F$29*(N3-'Assumptions & Log'!$F$26+1)*N7,0) -> 1210
B32: Marketplace revenue (net of referral fee), ₹ | C32: =C31*'Assumptions & Log'!$F$27*(1-'Assumptions & Log'!$F$28) -> 0 | D32: =D31*'Assumptions & Log'!$F$27*(1-'Assumptions & Log'!$F$28) -> 47155.167 | E32: =E31*'Assumptions & Log'!$F$27*(1-'Assumptions & Log'!$F$28) -> 98549 | F32: =F31*'Assumptions & Log'!$F$27*(1-'Assumptions & Log'!$F$28) -> 167692.25 | G32: =G31*'Assumptions & Log'!$F$27*(1-'Assumptions & Log'!$F$28) -> 216172 | H32: =H31*'Assumptions & Log'!$F$27*(1-'Assumptions & Log'!$F$28) -> 229152.92 | I32: =I31*'Assumptions & Log'!$F$27*(1-'Assumptions & Log'!$F$28) -> 286110 | J32: =J31*'Assumptions & Log'!$F$27*(1-'Assumptions & Log'!$F$28) -> 328231.75 | ... N32: =N31*'Assumptions & Log'!$F$27*(1-'Assumptions & Log'!$F$28) -> 699380
B33: Quick-commerce (Blinkit) orders | C33: =IF(C3>='Assumptions & Log'!$F$30,'Assumptions & Log'!$F$33*(C3-'Assumptions & Log'!$F$30+1)*C7,0) -> 0 | D33: =IF(D3>='Assumptions & Log'!$F$30,'Assumptions & Log'!$F$33*(D3-'Assumptions & Log'!$F$30+1)*D7,0) -> 0 | E33: =IF(E3>='Assumptions & Log'!$F$30,'Assumptions & Log'!$F$33*(E3-'Assumptions & Log'!$F$30+1)*E7,0) -> 69.75 | F33: =IF(F3>='Assumptions & Log'!$F$30,'Assumptions & Log'!$F$33*(F3-'Assumptions & Log'!$F$30+1)*F7,0) -> 158.25 | G33: =IF(G3>='Assumptions & Log'!$F$30,'Assumptions & Log'!$F$33*(G3-'Assumptions & Log'!$F$30+1)*G7,0) -> 229.5 | H33: =IF(H3>='Assumptions & Log'!$F$30,'Assumptions & Log'!$F$33*(H3-'Assumptions & Log'!$F$30+1)*H7,0) -> 259.5 | I33: =IF(I3>='Assumptions & Log'!$F$30,'Assumptions & Log'!$F$33*(I3-'Assumptions & Log'!$F$30+1)*I7,0) -> 337.5 | J33: =IF(J3>='Assumptions & Log'!$F$30,'Assumptions & Log'!$F$33*(J3-'Assumptions & Log'!$F$30+1)*J7,0) -> 398.25 | ... N33: =IF(N3>='Assumptions & Log'!$F$30,'Assumptions & Log'!$F$33*(N3-'Assumptions & Log'!$F$30+1)*N7,0) -> 900
B34: Quick-commerce revenue (net of trade margin), ₹ | C34: =C33*'Assumptions & Log'!$F$31*(1-'Assumptions & Log'!$F$32) -> 0 | D34: =D33*'Assumptions & Log'!$F$31*(1-'Assumptions & Log'!$F$32) -> 0 | E34: =E33*'Assumptions & Log'!$F$31*(1-'Assumptions & Log'!$F$32) -> 29016 | F34: =F33*'Assumptions & Log'!$F$31*(1-'Assumptions & Log'!$F$32) -> 65832 | G34: =G33*'Assumptions & Log'!$F$31*(1-'Assumptions & Log'!$F$32) -> 95472 | H34: =H33*'Assumptions & Log'!$F$31*(1-'Assumptions & Log'!$F$32) -> 107952 | I34: =I33*'Assumptions & Log'!$F$31*(1-'Assumptions & Log'!$F$32) -> 140400 | J34: =J33*'Assumptions & Log'!$F$31*(1-'Assumptions & Log'!$F$32) -> 165672 | ... N34: =N33*'Assumptions & Log'!$F$31*(1-'Assumptions & Log'!$F$32) -> 374400
B35: TOTAL NET REVENUE (MRR), ₹ | C35: =C30+C32+C34 -> 215641.05 | D35: =D30+D32+D34 -> 300654.36 | E35: =E30+E32+E34 -> 442991.86 | F35: =F30+F32+F34 -> 609814.02 | G35: =G30+G32+G34 -> 729803.94 | H35: =H30+H32+H34 -> 768754.26 | I35: =I30+I32+I34 -> 904329.83 | J35: =J30+J32+J34 -> 1013440.1 | ... N35: =N30+N32+N34 -> 2140610.4
B37: OPS: CANS & CAPACITY
B38: Cans per D2C order | C38: =6.2+1.4*C3/11 -> 6.2 | D38: =6.2+1.4*D3/11 -> 6.3272727 | E38: =6.2+1.4*E3/11 -> 6.4545455 | F38: =6.2+1.4*F3/11 -> 6.5818182 | G38: =6.2+1.4*G3/11 -> 6.7090909 | H38: =6.2+1.4*H3/11 -> 6.8363636 | I38: =6.2+1.4*I3/11 -> 6.9636364 | J38: =6.2+1.4*J3/11 -> 7.0909091 | ... N38: =6.2+1.4*N3/11 -> 7.6
B39: Cans required | C39: =C28*C38+C31*5.5+C33*3.5 -> 1612.7557 | D39: =D28*D38+D31*5.5+D33*3.5 -> 2362.4682 | E39: =E28*E38+E31*5.5+E33*3.5 -> 3584.619 | F39: =F28*F38+F31*5.5+F33*3.5 -> 5040.6438 | G39: =G28*G38+G31*5.5+G33*3.5 -> 6099.5185 | H39: =H28*H38+H31*5.5+H33*3.5 -> 6458.8952 | I39: =I28*I38+I31*5.5+I33*3.5 -> 7662.4597 | J39: =J28*J38+J31*5.5+J33*3.5 -> 8633.4703 | ... N39: =N28*N38+N31*5.5+N33*3.5 -> 18476.45
B40: Capacity ceiling (cans/month) | C40: ='Assumptions & Log'!$F$10+IF(C3>='Assumptions & Log'!$F$34+'Assumptions & Log'!$F$35,48000,0)+IF(C3>='Assumptions & Log'!$F$36+'Assumptions & Log'!$F$37,48000,0) -> 48000 | D40: ='Assumptions & Log'!$F$10+IF(D3>='Assumptions & Log'!$F$34+'Assumptions & Log'!$F$35,48000,0)+IF(D3>='Assumptions & Log'!$F$36+'Assumptions & Log'!$F$37,48000,0) -> 48000 | E40: ='Assumptions & Log'!$F$10+IF(E3>='Assumptions & Log'!$F$34+'Assumptions & Log'!$F$35,48000,0)+IF(E3>='Assumptions & Log'!$F$36+'Assumptions & Log'!$F$37,48000,0) -> 48000 | F40: ='Assumptions & Log'!$F$10+IF(F3>='Assumptions & Log'!$F$34+'Assumptions & Log'!$F$35,48000,0)+IF(F3>='Assumptions & Log'!$F$36+'Assumptions & Log'!$F$37,48000,0) -> 96000 | G40: ='Assumptions & Log'!$F$10+IF(G3>='Assumptions & Log'!$F$34+'Assumptions & Log'!$F$35,48000,0)+IF(G3>='Assumptions & Log'!$F$36+'Assumptions & Log'!$F$37,48000,0) -> 96000 | H40: ='Assumptions & Log'!$F$10+IF(H3>='Assumptions & Log'!$F$34+'Assumptions & Log'!$F$35,48000,0)+IF(H3>='Assumptions & Log'!$F$36+'Assumptions & Log'!$F$37,48000,0) -> 96000 | I40: ='Assumptions & Log'!$F$10+IF(I3>='Assumptions & Log'!$F$34+'Assumptions & Log'!$F$35,48000,0)+IF(I3>='Assumptions & Log'!$F$36+'Assumptions & Log'!$F$37,48000,0) -> 96000 | J40: ='Assumptions & Log'!$F$10+IF(J3>='Assumptions & Log'!$F$34+'Assumptions & Log'!$F$35,48000,0)+IF(J3>='Assumptions & Log'!$F$36+'Assumptions & Log'!$F$37,48000,0) -> 96000 | ... N40: ='Assumptions & Log'!$F$10+IF(N3>='Assumptions & Log'!$F$34+'Assumptions & Log'!$F$35,48000,0)+IF(N3>='Assumptions & Log'!$F$36+'Assumptions & Log'!$F$37,48000,0) -> 144000
B41: Capacity headroom (+) / shortfall (-) | C41: =C40-C39 -> 46387.244 | D41: =D40-D39 -> 45637.532 | E41: =E40-E39 -> 44415.381 | F41: =F40-F39 -> 90959.356 | G41: =G40-G39 -> 89900.482 | H41: =H40-H39 -> 89541.105 | I41: =I40-I39 -> 88337.54 | J41: =J40-J39 -> 87366.53 | ... N41: =N40-N39 -> 125523.55
B43: CONTRIBUTION MARGIN
B44: COGS per can, ₹ | C44: ='Assumptions & Log'!$F$41+('Assumptions & Log'!$F$42-'Assumptions & Log'!$F$41)*C3/11 -> 52 | D44: ='Assumptions & Log'!$F$41+('Assumptions & Log'!$F$42-'Assumptions & Log'!$F$41)*D3/11 -> 51.545455 | E44: ='Assumptions & Log'!$F$41+('Assumptions & Log'!$F$42-'Assumptions & Log'!$F$41)*E3/11 -> 51.090909 | F44: ='Assumptions & Log'!$F$41+('Assumptions & Log'!$F$42-'Assumptions & Log'!$F$41)*F3/11 -> 50.636364 | G44: ='Assumptions & Log'!$F$41+('Assumptions & Log'!$F$42-'Assumptions & Log'!$F$41)*G3/11 -> 50.181818 | H44: ='Assumptions & Log'!$F$41+('Assumptions & Log'!$F$42-'Assumptions & Log'!$F$41)*H3/11 -> 49.727273 | I44: ='Assumptions & Log'!$F$41+('Assumptions & Log'!$F$42-'Assumptions & Log'!$F$41)*I3/11 -> 49.272727 | J44: ='Assumptions & Log'!$F$41+('Assumptions & Log'!$F$42-'Assumptions & Log'!$F$41)*J3/11 -> 48.818182 | ... N44: ='Assumptions & Log'!$F$41+('Assumptions & Log'!$F$42-'Assumptions & Log'!$F$41)*N3/11 -> 47
B45: COGS, ₹ | C45: =C39*C44 -> 83863.298 | D45: =D39*D44 -> 121774.5 | E45: =E39*E44 -> 183141.44 | F45: =F39*F44 -> 255239.87 | G45: =G39*G44 -> 306084.93 | H45: =H39*H44 -> 321183.24 | I45: =I39*I44 -> 377550.29 | J45: =J39*J44 -> 421470.32 | ... N45: =N39*N44 -> 868393.17
B46: Shipping per order, ₹ | C46: ='Assumptions & Log'!$F$43+('Assumptions & Log'!$F$44-'Assumptions & Log'!$F$43)*C3/11 -> 76 | D46: ='Assumptions & Log'!$F$43+('Assumptions & Log'!$F$44-'Assumptions & Log'!$F$43)*D3/11 -> 74.909091 | E46: ='Assumptions & Log'!$F$43+('Assumptions & Log'!$F$44-'Assumptions & Log'!$F$43)*E3/11 -> 73.818182 | F46: ='Assumptions & Log'!$F$43+('Assumptions & Log'!$F$44-'Assumptions & Log'!$F$43)*F3/11 -> 72.727273 | G46: ='Assumptions & Log'!$F$43+('Assumptions & Log'!$F$44-'Assumptions & Log'!$F$43)*G3/11 -> 71.636364 | H46: ='Assumptions & Log'!$F$43+('Assumptions & Log'!$F$44-'Assumptions & Log'!$F$43)*H3/11 -> 70.545455 | I46: ='Assumptions & Log'!$F$43+('Assumptions & Log'!$F$44-'Assumptions & Log'!$F$43)*I3/11 -> 69.454545 | J46: ='Assumptions & Log'!$F$43+('Assumptions & Log'!$F$44-'Assumptions & Log'!$F$43)*J3/11 -> 68.363636 | ... N46: ='Assumptions & Log'!$F$43+('Assumptions & Log'!$F$44-'Assumptions & Log'!$F$43)*N3/11 -> 64
B47: Shipping & fulfilment, ₹ | C47: =(C28+C31+C33)*C46*0.6 -> 11861.558 | D47: =(D28+D31+D33)*D46*0.6 -> 17261.094 | E47: =(E28+E31+E33)*E46*0.6 -> 27128.452 | F47: =(F28+F31+F33)*F46*0.6 -> 38732.844 | G47: =(G28+G31+G33)*G46*0.6 -> 46691.914 | H47: =(H28+H31+H33)*H46*0.6 -> 48631.016 | I47: =(I28+I31+I33)*I46*0.6 -> 57185.921 | J47: =(J28+J31+J33)*J46*0.6 -> 63439.804 | ... N47: =(N28+N31+N33)*N46*0.6 -> 124837.64
B48: Payment gateway fees, ₹ | C48: =C35*'Assumptions & Log'!$F$45 -> 4312.821 | D48: =D35*'Assumptions & Log'!$F$45 -> 6013.0871 | E48: =E35*'Assumptions & Log'!$F$45 -> 8859.8372 | F48: =F35*'Assumptions & Log'!$F$45 -> 12196.28 | G48: =G35*'Assumptions & Log'!$F$45 -> 14596.079 | H48: =H35*'Assumptions & Log'!$F$45 -> 15375.085 | I48: =I35*'Assumptions & Log'!$F$45 -> 18086.597 | J48: =J35*'Assumptions & Log'!$F$45 -> 20268.801 | ... N48: =N35*'Assumptions & Log'!$F$45 -> 42812.209
B49: Boxes & packaging, ₹ | C49: =C28*'Assumptions & Log'!$F$46 -> 5722.6816 | D49: =D28*'Assumptions & Log'!$F$46 -> 6654.1651 | E49: =E28*'Assumptions & Log'!$F$46 -> 8189.6344 | F49: =F28*'Assumptions & Log'!$F$46 -> 9663.5589 | G49: =G28*'Assumptions & Log'!$F$46 -> 10621.991 | H49: =H28*'Assumptions & Log'!$F$46 -> 10845.347 | I49: =I28*'Assumptions & Log'!$F$46 -> 11874.775 | J49: =J28*'Assumptions & Log'!$F$46 -> 12771.031 | ... N49: =N28*'Assumptions & Log'!$F$46 -> 25101.567
B50: Contribution Margin 1, ₹ | C50: =C35-C45-C47-C48-C49 -> 109880.69 | D50: =D35-D45-D47-D48-D49 -> 148951.51 | E50: =E35-E45-E47-E48-E49 -> 215672.5 | F50: =F35-F45-F47-F48-F49 -> 293981.47 | G50: =G35-G45-G47-G48-G49 -> 351809.02 | H50: =H35-H45-H47-H48-H49 -> 372719.56 | I50: =I35-I45-I47-I48-I49 -> 439632.25 | J50: =J35-J45-J47-J48-J49 -> 495490.1 | ... N50: =N35-N45-N47-N48-N49 -> 1079465.8
B51: CM1 % of revenue | C51: =C50/C35 -> 0.50955368 | D51: =D50/D35 -> 0.49542443 | E51: =E50/E35 -> 0.48685431 | F51: =F50/F35 -> 0.48208381 | G51: =G50/G35 -> 0.48205964 | H51: =H50/H35 -> 0.48483577 | I51: =I50/I35 -> 0.48614149 | J51: =J50/J35 -> 0.488919 | ... N51: =N50/N35 -> 0.50427945
B53: MARKETING & OVERHEAD
B54: Influencer seeding, ₹ | C54: =IF(C7>=1,8500,6000) -> 6000 | D54: =IF(D7>=1,8500,6000) -> 6000 | E54: =IF(E7>=1,8500,6000) -> 6000 | F54: =IF(F7>=1,8500,6000) -> 6000 | G54: =IF(G7>=1,8500,6000) -> 6000 | H54: =IF(H7>=1,8500,6000) -> 6000 | I54: =IF(I7>=1,8500,6000) -> 6000 | J54: =IF(J7>=1,8500,6000) -> 6000 | ... N54: =IF(N7>=1,8500,6000) -> 8500
B55: Tools & software, ₹ | C55: =6500+150*C3 -> 6500 | D55: =6500+150*D3 -> 6650 | E55: =6500+150*E3 -> 6800 | F55: =6500+150*F3 -> 6950 | G55: =6500+150*G3 -> 7100 | H55: =6500+150*H3 -> 7250 | I55: =6500+150*I3 -> 7400 | J55: =6500+150*J3 -> 7550 | ... N55: =6500+150*N3 -> 8150
B56: Total marketing cost (paid+seeding+tools), ₹ | C56: =C10+C54+C55 -> 127500 | D56: =D10+D54+D55 -> 133400 | E56: =E10+E54+E55 -> 139587.5 | F56: =F10+F54+F55 -> 146076.88 | G56: =G10+G54+G55 -> 152883.22 | H56: =H10+H54+H55 -> 160022.38 | I56: =I10+I54+I55 -> 167511 | J56: =J10+J54+J55 -> 175366.55 | ... N56: =N10+N54+N55 -> 256708.73
B57: Contribution Margin 2, ₹ | C57: =C50-C56 -> -17619.31 | D57: =D50-D56 -> 15551.513 | E57: =E50-E56 -> 76084.995 | F57: =F50-F56 -> 147904.59 | G57: =G50-G56 -> 198925.81 | H57: =H50-H56 -> 212697.18 | I57: =I50-I56 -> 272121.25 | J57: =J50-J56 -> 320123.55 | ... N57: =N50-N56 -> 822757.11
B58: Incremental hiring cost, ₹ | C58: =IF(C3>='Assumptions & Log'!$F$49,'Assumptions & Log'!$F$50,0)+IF(C3>='Assumptions & Log'!$F$51,'Assumptions & Log'!$F$52,0)+IF(C3>='Assumptions & Log'!$F$53,'Assumptions & Log'!$F$54,0) -> 0 | D58: =IF(D3>='Assumptions & Log'!$F$49,'Assumptions & Log'!$F$50,0)+IF(D3>='Assumptions & Log'!$F$51,'Assumptions & Log'!$F$52,0)+IF(D3>='Assumptions & Log'!$F$53,'Assumptions & Log'!$F$54,0) -> 0 | E58: =IF(E3>='Assumptions & Log'!$F$49,'Assumptions & Log'!$F$50,0)+IF(E3>='Assumptions & Log'!$F$51,'Assumptions & Log'!$F$52,0)+IF(E3>='Assumptions & Log'!$F$53,'Assumptions & Log'!$F$54,0) -> 40000 | F58: =IF(F3>='Assumptions & Log'!$F$49,'Assumptions & Log'!$F$50,0)+IF(F3>='Assumptions & Log'!$F$51,'Assumptions & Log'!$F$52,0)+IF(F3>='Assumptions & Log'!$F$53,'Assumptions & Log'!$F$54,0) -> 40000 | G58: =IF(G3>='Assumptions & Log'!$F$49,'Assumptions & Log'!$F$50,0)+IF(G3>='Assumptions & Log'!$F$51,'Assumptions & Log'!$F$52,0)+IF(G3>='Assumptions & Log'!$F$53,'Assumptions & Log'!$F$54,0) -> 40000 | H58: =IF(H3>='Assumptions & Log'!$F$49,'Assumptions & Log'!$F$50,0)+IF(H3>='Assumptions & Log'!$F$51,'Assumptions & Log'!$F$52,0)+IF(H3>='Assumptions & Log'!$F$53,'Assumptions & Log'!$F$54,0) -> 75000 | I58: =IF(I3>='Assumptions & Log'!$F$49,'Assumptions & Log'!$F$50,0)+IF(I3>='Assumptions & Log'!$F$51,'Assumptions & Log'!$F$52,0)+IF(I3>='Assumptions & Log'!$F$53,'Assumptions & Log'!$F$54,0) -> 75000 | J58: =IF(J3>='Assumptions & Log'!$F$49,'Assumptions & Log'!$F$50,0)+IF(J3>='Assumptions & Log'!$F$51,'Assumptions & Log'!$F$52,0)+IF(J3>='Assumptions & Log'!$F$53,'Assumptions & Log'!$F$54,0) -> 75000 | ... N58: =IF(N3>='Assumptions & Log'!$F$49,'Assumptions & Log'!$F$50,0)+IF(N3>='Assumptions & Log'!$F$51,'Assumptions & Log'!$F$52,0)+IF(N3>='Assumptions & Log'!$F$53,'Assumptions & Log'!$F$54,0) -> 115000
B59: Fixed overhead (salaries+freelance+3PL+admin), ₹ | C59: =110000+C58+18000+9500+8000 -> 145500 | D59: =110000+D58+18000+9500+8000 -> 145500 | E59: =110000+E58+18000+9500+8000 -> 185500 | F59: =110000+F58+18000+9500+8000 -> 185500 | G59: =110000+G58+18000+9500+8000 -> 185500 | H59: =110000+H58+18000+9500+8000 -> 220500 | I59: =110000+I58+18000+9500+8000 -> 220500 | J59: =110000+J58+18000+9500+8000 -> 220500 | ... N59: =110000+N58+18000+9500+8000 -> 260500
B60: EBITDA, ₹ | C60: =C57-C59 -> -163119.31 | D60: =D57-D59 -> -129948.49 | E60: =E57-E59 -> -109415 | F60: =F57-F59 -> -37595.406 | G60: =G57-G59 -> 13425.806 | H60: =H57-H59 -> -7802.8154 | I60: =I57-I59 -> 51621.248 | J60: =J57-J59 -> 99623.554 | ... N60: =N57-N59 -> 562257.11
B62: CASH
B63: Working-capital drag (batch advance timing), ₹ | C63: =C45*'Assumptions & Log'!$F$47 -> 12579.495 | D63: =D45*'Assumptions & Log'!$F$47 -> 18266.175 | E63: =E45*'Assumptions & Log'!$F$47 -> 27471.216 | F63: =F45*'Assumptions & Log'!$F$47 -> 38285.981 | G63: =G45*'Assumptions & Log'!$F$47 -> 45912.739 | H63: =H45*'Assumptions & Log'!$F$47 -> 48177.486 | I63: =I45*'Assumptions & Log'!$F$47 -> 56632.543 | J63: =J45*'Assumptions & Log'!$F$47 -> 63220.549 | ... N63: =N45*'Assumptions & Log'!$F$47 -> 130258.98
B64: Capacity-expansion capex, ₹ | C64: =IF(C3='Assumptions & Log'!$F$34,'Assumptions & Log'!$F$48,0)+IF(C3='Assumptions & Log'!$F$36,'Assumptions & Log'!$F$48,0) -> 0 | D64: =IF(D3='Assumptions & Log'!$F$34,'Assumptions & Log'!$F$48,0)+IF(D3='Assumptions & Log'!$F$36,'Assumptions & Log'!$F$48,0) -> 600000 | E64: =IF(E3='Assumptions & Log'!$F$34,'Assumptions & Log'!$F$48,0)+IF(E3='Assumptions & Log'!$F$36,'Assumptions & Log'!$F$48,0) -> 0 | F64: =IF(F3='Assumptions & Log'!$F$34,'Assumptions & Log'!$F$48,0)+IF(F3='Assumptions & Log'!$F$36,'Assumptions & Log'!$F$48,0) -> 0 | G64: =IF(G3='Assumptions & Log'!$F$34,'Assumptions & Log'!$F$48,0)+IF(G3='Assumptions & Log'!$F$36,'Assumptions & Log'!$F$48,0) -> 0 | H64: =IF(H3='Assumptions & Log'!$F$34,'Assumptions & Log'!$F$48,0)+IF(H3='Assumptions & Log'!$F$36,'Assumptions & Log'!$F$48,0) -> 0 | I64: =IF(I3='Assumptions & Log'!$F$34,'Assumptions & Log'!$F$48,0)+IF(I3='Assumptions & Log'!$F$36,'Assumptions & Log'!$F$48,0) -> 0 | J64: =IF(J3='Assumptions & Log'!$F$34,'Assumptions & Log'!$F$48,0)+IF(J3='Assumptions & Log'!$F$36,'Assumptions & Log'!$F$48,0) -> 600000 | ... N64: =IF(N3='Assumptions & Log'!$F$34,'Assumptions & Log'!$F$48,0)+IF(N3='Assumptions & Log'!$F$36,'Assumptions & Log'!$F$48,0) -> 0
B65: Funding raise, ₹ | C65: =IF(C3='Assumptions & Log'!$F$55,'Assumptions & Log'!$F$56,0) -> 0 | D65: =IF(D3='Assumptions & Log'!$F$55,'Assumptions & Log'!$F$56,0) -> 0 | E65: =IF(E3='Assumptions & Log'!$F$55,'Assumptions & Log'!$F$56,0) -> 0 | F65: =IF(F3='Assumptions & Log'!$F$55,'Assumptions & Log'!$F$56,0) -> 0 | G65: =IF(G3='Assumptions & Log'!$F$55,'Assumptions & Log'!$F$56,0) -> 0 | H65: =IF(H3='Assumptions & Log'!$F$55,'Assumptions & Log'!$F$56,0) -> 0 | I65: =IF(I3='Assumptions & Log'!$F$55,'Assumptions & Log'!$F$56,0) -> 0 | J65: =IF(J3='Assumptions & Log'!$F$55,'Assumptions & Log'!$F$56,0) -> 0 | ... N65: =IF(N3='Assumptions & Log'!$F$55,'Assumptions & Log'!$F$56,0) -> 0
B66: Cash — beginning, ₹ | C66: ='Assumptions & Log'!$F$6 -> 3140000 | D66: =C67 -> 2964301.2 | E66: =D67 -> 2216086.5 | F66: =E67 -> 2079200.3 | G66: =F67 -> 2003318.9 | H66: =G67 -> 1970832 | I66: =H67 -> 1914851.7 | J66: =I67 -> 1909840.4 | K66: =J67 -> 1346243.4 | ... N66: =M67 -> 2011481.2
B67: Cash — ending, ₹ | C67: =C66+C60-C63-C64+C65 -> 2964301.2 | D67: =D66+D60-D63-D64+D65 -> 2216086.5 | E67: =E66+E60-E63-E64+E65 -> 2079200.3 | F67: =F66+F60-F63-F64+F65 -> 2003318.9 | G67: =G66+G60-G63-G64+G65 -> 1970832 | H67: =H66+H60-H63-H64+H65 -> 1914851.7 | I67: =I66+I60-I63-I64+I65 -> 1909840.4 | J67: =J66+J60-J63-J64+J65 -> 1346243.4 | ... N67: =N66+N60-N63-N64+N65 -> 2443479.3
B68: Below ₹5L covenant floor? | C68: =IF(C67<'Assumptions & Log'!$F$57,"BREACH","ok") -> ok | D68: =IF(D67<'Assumptions & Log'!$F$57,"BREACH","ok") -> ok | E68: =IF(E67<'Assumptions & Log'!$F$57,"BREACH","ok") -> ok | F68: =IF(F67<'Assumptions & Log'!$F$57,"BREACH","ok") -> ok | G68: =IF(G67<'Assumptions & Log'!$F$57,"BREACH","ok") -> ok | H68: =IF(H67<'Assumptions & Log'!$F$57,"BREACH","ok") -> ok | I68: =IF(I67<'Assumptions & Log'!$F$57,"BREACH","ok") -> ok | J68: =IF(J67<'Assumptions & Log'!$F$57,"BREACH","ok") -> ok | ... N68: =IF(N67<'Assumptions & Log'!$F$57,"BREACH","ok") -> ok

Sheet Weekly Rollout
A1: WEEKLY ROLLOUT — 52 WEEKS (Jul 1, 2026 – Jun 29, 2027)
A2: Each week = its month's Monthly Engine total x a within-month weight (weights sum to 1 -> weekly rows always tie back to the monthly engine exactly). Only new-customer acquisition + total revenue carry the weekly weighting; capacity is shown as an even monthly split for headroom-checking.
A4: Wk | B4: Start | C4: End | D4: Month | E4: Wk wt | F4: New Paid Ord | G4: New Org Ord | H4: D2C Orders | I4: Mkt+QC Ord | J4: Total Orders | K4: AOV ₹ | L4: Net Revenue ₹ | M4: Cans Req'd | N4: Capacity/wk | O4: Headroom | P4: CM1 ₹ | Q4: EBITDA (flow) ₹ | R4: Event note
A5: F1 | B5: 46204 | C5: 46210 | D5: Jul-26 | E5: 0.25 | F5: =INDEX('Monthly Engine'!$C$13:$N$13,MATCH($D5,'Monthly Engine'!$C$4:$N$4,0))*$E5 -> 42.647173 | G5: =INDEX('Monthly Engine'!$C$14:$N$14,MATCH($D5,'Monthly Engine'!$C$4:$N$4,0))*$E5 -> 8.3899583 | H5: =INDEX('Monthly Engine'!$C$28:$N$28,MATCH($D5,'Monthly Engine'!$C$4:$N$4,0))*$E5 -> 65.030473 | I5: =(INDEX('Monthly Engine'!$C$31:$N$31,MATCH($D5,'Monthly Engine'!$C$4:$N$4,0))+INDEX('Monthly Engine'!$C$33:$N$33,MATCH($D5,'Monthly Engine'!$C$4:$N$4,0)))*$E5 -> 0 | J5: =H5+I5 -> 65.030473 | K5: =INDEX('Monthly Engine'!$C$29:$N$29,MATCH($D5,'Monthly Engine'!$C$4:$N$4,0)) -> 829 | L5: =INDEX('Monthly Engine'!$C$35:$N$35,MATCH($D5,'Monthly Engine'!$C$4:$N$4,0))*$E5 -> 53910.262 | M5: =INDEX('Monthly Engine'!$C$39:$N$39,MATCH($D5,'Monthly Engine'!$C$4:$N$4,0))*$E5 -> 403.18893 | N5: =INDEX('Monthly Engine'!$C$40:$N$40,MATCH($D5,'Monthly Engine'!$C$4:$N$4,0))/4 -> 12000 | O5: =N5-M5 -> 11596.811 | P5: =INDEX('Monthly Engine'!$C$50:$N$50,MATCH($D5,'Monthly Engine'!$C$4:$N$4,0))*$E5 -> 27470.172 | Q5: =INDEX('Monthly Engine'!$C$60:$N$60,MATCH($D5,'Monthly Engine'!$C$4:$N$4,0))*$E5 -> -40779.828
A6: F2 | B6: 46211 | C6: 46217 | D6: Jul-26 | E6: 0.25 | F6: =INDEX('Monthly Engine'!$C$13:$N$13,MATCH($D6,'Monthly Engine'!$C$4:$N$4,0))*$E6 -> 42.647173 | G6: =INDEX('Monthly Engine'!$C$14:$N$14,MATCH($D6,'Monthly Engine'!$C$4:$N$4,0))*$E6 -> 8.3899583 | H6: =INDEX('Monthly Engine'!$C$28:$N$28,MATCH($D6,'Monthly Engine'!$C$4:$N$4,0))*$E6 -> 65.030473 | I6: =(INDEX('Monthly Engine'!$C$31:$N$31,MATCH($D6,'Monthly Engine'!$C$4:$N$4,0))+INDEX('Monthly Engine'!$C$33:$N$33,MATCH($D6,'Monthly Engine'!$C$4:$N$4,0)))*$E6 -> 0 | J6: =H6+I6 -> 65.030473 | K6: =INDEX('Monthly Engine'!$C$29:$N$29,MATCH($D6,'Monthly Engine'!$C$4:$N$4,0)) -> 829 | L6: =INDEX('Monthly Engine'!$C$35:$N$35,MATCH($D6,'Monthly Engine'!$C$4:$N$4,0))*$E6 -> 53910.262 | M6: =INDEX('Monthly Engine'!$C$39:$N$39,MATCH($D6,'Monthly Engine'!$C$4:$N$4,0))*$E6 -> 403.18893 | N6: =INDEX('Monthly Engine'!$C$40:$N$40,MATCH($D6,'Monthly Engine'!$C$4:$N$4,0))/4 -> 12000 | O6: =N6-M6 -> 11596.811 | P6: =INDEX('Monthly Engine'!$C$50:$N$50,MATCH($D6,'Monthly Engine'!$C$4:$N$4,0))*$E6 -> 27470.172 | Q6: =INDEX('Monthly Engine'!$C$60:$N$60,MATCH($D6,'Monthly Engine'!$C$4:$N$4,0))*$E6 -> -40779.828
A7: F3 | B7: 46218 | C7: 46224 | D7: Jul-26 | E7: 0.25 | F7: =INDEX('Monthly Engine'!$C$13:$N$13,MATCH($D7,'Monthly Engine'!$C$4:$N$4,0))*$E7 -> 42.647173 | G7: =INDEX('Monthly Engine'!$C$14:$N$14,MATCH($D7,'Monthly Engine'!$C$4:$N$4,0))*$E7 -> 8.3899583 | H7: =INDEX('Monthly Engine'!$C$28:$N$28,MATCH($D7,'Monthly Engine'!$C$4:$N$4,0))*$E7 -> 65.030473 | I7: =(INDEX('Monthly Engine'!$C$31:$N$31,MATCH($D7,'Monthly Engine'!$C$4:$N$4,0))+INDEX('Monthly Engine'!$C$33:$N$33,MATCH($D7,'Monthly Engine'!$C$4:$N$4,0)))*$E7 -> 0 | J7: =H7+I7 -> 65.030473 | K7: =INDEX('Monthly Engine'!$C$29:$N$29,MATCH($D7,'Monthly Engine'!$C$4:$N$4,0)) -> 829 | L7: =INDEX('Monthly Engine'!$C$35:$N$35,MATCH($D7,'Monthly Engine'!$C$4:$N$4,0))*$E7 -> 53910.262 | M7: =INDEX('Monthly Engine'!$C$39:$N$39,MATCH($D7,'Monthly Engine'!$C$4:$N$4,0))*$E7 -> 403.18893 | N7: =INDEX('Monthly Engine'!$C$40:$N$40,MATCH($D7,'Monthly Engine'!$C$4:$N$4,0))/4 -> 12000 | O7: =N7-M7 -> 11596.811 | P7: =INDEX('Monthly Engine'!$C$50:$N$50,MATCH($D7,'Monthly Engine'!$C$4:$N$4,0))*$E7 -> 27470.172 | Q7: =INDEX('Monthly Engine'!$C$60:$N$60,MATCH($D7,'Monthly Engine'!$C$4:$N$4,0))*$E7 -> -40779.828
A8: F4 | B8: 46225 | C8: 46231 | D8: Jul-26 | E8: 0.25 | F8: =INDEX('Monthly Engine'!$C$13:$N$13,MATCH($D8,'Monthly Engine'!$C$4:$N$4,0))*$E8 -> 42.647173 | G8: =INDEX('Monthly Engine'!$C$14:$N$14,MATCH($D8,'Monthly Engine'!$C$4:$N$4,0))*$E8 -> 8.3899583 | H8: =INDEX('Monthly Engine'!$C$28:$N$28,MATCH($D8,'Monthly Engine'!$C$4:$N$4,0))*$E8 -> 65.030473 | I8: =(INDEX('Monthly Engine'!$C$31:$N$31,MATCH($D8,'Monthly Engine'!$C$4:$N$4,0))+INDEX('Monthly Engine'!$C$33:$N$33,MATCH($D8,'Monthly Engine'!$C$4:$N$4,0)))*$E8 -> 0 | J8: =H8+I8 -> 65.030473 | K8: =INDEX('Monthly Engine'!$C$29:$N$29,MATCH($D8,'Monthly Engine'!$C$4:$N$4,0)) -> 829 | L8: =INDEX('Monthly Engine'!$C$35:$N$35,MATCH($D8,'Monthly Engine'!$C$4:$N$4,0))*$E8 -> 53910.262 | M8: =INDEX('Monthly Engine'!$C$39:$N$39,MATCH($D8,'Monthly Engine'!$C$4:$N$4,0))*$E8 -> 403.18893 | N8: =INDEX('Monthly Engine'!$C$40:$N$40,MATCH($D8,'Monthly Engine'!$C$4:$N$4,0))/4 -> 12000 | O8: =N8-M8 -> 11596.811 | P8: =INDEX('Monthly Engine'!$C$50:$N$50,MATCH($D8,'Monthly Engine'!$C$4:$N$4,0))*$E8 -> 27470.172 | Q8: =INDEX('Monthly Engine'!$C$60:$N$60,MATCH($D8,'Monthly Engine'!$C$4:$N$4,0))*$E8 -> -40779.828
A9: F5 | B9: 46232 | C9: 46238 | D9: Aug-26 | E9: 0.2 | F9: =INDEX('Monthly Engine'!$C$13:$N$13,MATCH($D9,'Monthly Engine'!$C$4:$N$4,0))*$E9 -> 32.924426 | G9: =INDEX('Monthly Engine'!$C$14:$N$14,MATCH($D9,'Monthly Engine'!$C$4:$N$4,0))*$E9 -> 7.5843651 | H9: =INDEX('Monthly Engine'!$C$28:$N$28,MATCH($D9,'Monthly Engine'!$C$4:$N$4,0))*$E9 -> 60.49241 | I9: =(INDEX('Monthly Engine'!$C$31:$N$31,MATCH($D9,'Monthly Engine'!$C$4:$N$4,0))+INDEX('Monthly Engine'!$C$33:$N$33,MATCH($D9,'Monthly Engine'!$C$4:$N$4,0)))*$E9 -> 16.316667 | J9: =H9+I9 -> 76.809077 | K9: =INDEX('Monthly Engine'!$C$29:$N$29,MATCH($D9,'Monthly Engine'!$C$4:$N$4,0)) -> 838.119 | L9: =INDEX('Monthly Engine'!$C$35:$N$35,MATCH($D9,'Monthly Engine'!$C$4:$N$4,0))*$E9 -> 60130.871 | M9: =INDEX('Monthly Engine'!$C$39:$N$39,MATCH($D9,'Monthly Engine'!$C$4:$N$4,0))*$E9 -> 472.49364 | N9: =INDEX('Monthly Engine'!$C$40:$N$40,MATCH($D9,'Monthly Engine'!$C$4:$N$4,0))/5 -> 9600 | O9: =N9-M9 -> 9127.5064 | P9: =INDEX('Monthly Engine'!$C$50:$N$50,MATCH($D9,'Monthly Engine'!$C$4:$N$4,0))*$E9 -> 29790.303 | Q9: =INDEX('Monthly Engine'!$C$60:$N$60,MATCH($D9,'Monthly Engine'!$C$4:$N$4,0))*$E9 -> -25989.697
A10: F6 | B10: 46239 | C10: 46245 | D10: Aug-26 | E10: 0.2 | F10: =INDEX('Monthly Engine'!$C$13:$N$13,MATCH($D10,'Monthly Engine'!$C$4:$N$4,0))*$E10 -> 32.924426 | G10: =INDEX('Monthly Engine'!$C$14:$N$14,MATCH($D10,'Monthly Engine'!$C$4:$N$4,0))*$E10 -> 7.5843651 | H10: =INDEX('Monthly Engine'!$C$28:$N$28,MATCH($D10,'Monthly Engine'!$C$4:$N$4,0))*$E10 -> 60.49241 | I10: =(INDEX('Monthly Engine'!$C$31:$N$31,MATCH($D10,'Monthly Engine'!$C$4:$N$4,0))+INDEX('Monthly Engine'!$C$33:$N$33,MATCH($D10,'Monthly Engine'!$C$4:$N$4,0)))*$E10 -> 16.316667 | J10: =H10+I10 -> 76.809077 | K10: =INDEX('Monthly Engine'!$C$29:$N$29,MATCH($D10,'Monthly Engine'!$C$4:$N$4,0)) -> 838.119 | L10: =INDEX('Monthly Engine'!$C$35:$N$35,MATCH($D10,'Monthly Engine'!$C$4:$N$4,0))*$E10 -> 60130.871 | M10: =INDEX('Monthly Engine'!$C$39:$N$39,MATCH($D10,'Monthly Engine'!$C$4:$N$4,0))*$E10 -> 472.49364 | N10: =INDEX('Monthly Engine'!$C$40:$N$40,MATCH($D10,'Monthly Engine'!$C$4:$N$4,0))/5 -> 9600 | O10: =N10-M10 -> 9127.5064 | P10: =INDEX('Monthly Engine'!$C$50:$N$50,MATCH($D10,'Monthly Engine'!$C$4:$N$4,0))*$E10 -> 29790.303 | Q10: =INDEX('Monthly Engine'!$C$60:$N$60,MATCH($D10,'Monthly Engine'!$C$4:$N$4,0))*$E10 -> -25989.697
A11: F7 | B11: 46246 | C11: 46252 | D11: Aug-26 | E11: 0.2 | F11: =INDEX('Monthly Engine'!$C$13:$N$13,MATCH($D11,'Monthly Engine'!$C$4:$N$4,0))*$E11 -> 32.924426 | G11: =INDEX('Monthly Engine'!$C$14:$N$14,MATCH($D11,'Monthly Engine'!$C$4:$N$4,0))*$E11 -> 7.5843651 | H11: =INDEX('Monthly Engine'!$C$28:$N$28,MATCH($D11,'Monthly Engine'!$C$4:$N$4,0))*$E11 -> 60.49241 | I11: =(INDEX('Monthly Engine'!$C$31:$N$31,MATCH($D11,'Monthly Engine'!$C$4:$N$4,0))+INDEX('Monthly Engine'!$C$33:$N$33,MATCH($D11,'Monthly Engine'!$C$4:$N$4,0)))*$E11 -> 16.316667 | J11: =H11+I11 -> 76.809077 | K11: =INDEX('Monthly Engine'!$C$29:$N$29,MATCH($D11,'Monthly Engine'!$C$4:$N$4,0)) -> 838.119 | L11: =INDEX('Monthly Engine'!$C$35:$N$35,MATCH($D11,'Monthly Engine'!$C$4:$N$4,0))*$E11 -> 60130.871 | M11: =INDEX('Monthly Engine'!$C$39:$N$39,MATCH($D11,'Monthly Engine'!$C$4:$N$4,0))*$E11 -> 472.49364 | N11: =INDEX('Monthly Engine'!$C$40:$N$40,MATCH($D11,'Monthly Engine'!$C$4:$N$4,0))/5 -> 9600 | O11: =N11-M11 -> 9127.5064 | P11: =INDEX('Monthly Engine'!$C$50:$N$50,MATCH($D11,'Monthly Engine'!$C$4:$N$4,0))*$E11 -> 29790.303 | Q11: =INDEX('Monthly Engine'!$C$60:$N$60,MATCH($D11,'Monthly Engine'!$C$4:$N$4,0))*$E11 -> -25989.697
A12: F8 | B12: 46253 | C12: 46259 | D12: Aug-26 | E12: 0.2 | F12: =INDEX('Monthly Engine'!$C$13:$N$13,MATCH($D12,'Monthly Engine'!$C$4:$N$4,0))*$E12 -> 32.924426 | G12: =INDEX('Monthly Engine'!$C$14:$N$14,MATCH($D12,'Monthly Engine'!$C$4:$N$4,0))*$E12 -> 7.5843651 | H12: =INDEX('Monthly Engine'!$C$28:$N$28,MATCH($D12,'Monthly Engine'!$C$4:$N$4,0))*$E12 -> 60.49241 | I12: =(INDEX('Monthly Engine'!$C$31:$N$31,MATCH($D12,'Monthly Engine'!$C$4:$N$4,0))+INDEX('Monthly Engine'!$C$33:$N$33,MATCH($D12,'Monthly Engine'!$C$4:$N$4,0)))*$E12 -> 16.316667 | J12: =H12+I12 -> 76.809077 | K12: =INDEX('Monthly Engine'!$C$29:$N$29,MATCH($D12,'Monthly Engine'!$C$4:$N$4,0)) -> 838.119 | L12: =INDEX('Monthly Engine'!$C$35:$N$35,MATCH($D12,'Monthly Engine'!$C$4:$N$4,0))*$E12 -> 60130.871 | M12: =INDEX('Monthly Engine'!$C$39:$N$39,MATCH($D12,'Monthly Engine'!$C$4:$N$4,0))*$E12 -> 472.49364 | N12: =INDEX('Monthly Engine'!$C$40:$N$40,MATCH($D12,'Monthly Engine'!$C$4:$N$4,0))/5 -> 9600 | O12: =N12-M12 -> 9127.5064 | P12: =INDEX('Monthly Engine'!$C$50:$N$50,MATCH($D12,'Monthly Engine'!$C$4:$N$4,0))*$E12 -> 29790.303 | Q12: =INDEX('Monthly Engine'!$C$60:$N$60,MATCH($D12,'Monthly Engine'!$C$4:$N$4,0))*$E12 -> -25989.697
A13: F9 | B13: 46260 | C13: 46266 | D13: Aug-26 | E13: 0.2 | F13: =INDEX('Monthly Engine'!$C$13:$N$13,MATCH($D13,'Monthly Engine'!$C$4:$N$4,0))*$E13 -> 32.924426 | G13: =INDEX('Monthly Engine'!$C$14:$N$14,MATCH($D13,'Monthly Engine'!$C$4:$N$4,0))*$E13 -> 7.5843651 | H13: =INDEX('Monthly Engine'!$C$28:$N$28,MATCH($D13,'Monthly Engine'!$C$4:$N$4,0))*$E13 -> 60.49241 | I13: =(INDEX('Monthly Engine'!$C$31:$N$31,MATCH($D13,'Monthly Engine'!$C$4:$N$4,0))+INDEX('Monthly Engine'!$C$33:$N$33,MATCH($D13,'Monthly Engine'!$C$4:$N$4,0)))*$E13 -> 16.316667 | J13: =H13+I13 -> 76.809077 | K13: =INDEX('Monthly Engine'!$C$29:$N$29,MATCH($D13,'Monthly Engine'!$C$4:$N$4,0)) -> 838.119 | L13: =INDEX('Monthly Engine'!$C$35:$N$35,MATCH($D13,'Monthly Engine'!$C$4:$N$4,0))*$E13 -> 60130.871 | M13: =INDEX('Monthly Engine'!$C$39:$N$39,MATCH($D13,'Monthly Engine'!$C$4:$N$4,0))*$E13 -> 472.49364 | N13: =INDEX('Monthly Engine'!$C$40:$N$40,MATCH($D13,'Monthly Engine'!$C$4:$N$4,0))/5 -> 9600 | O13: =N13-M13 -> 9127.5064 | P13: =INDEX('Monthly Engine'!$C$50:$N$50,MATCH($D13,'Monthly Engine'!$C$4:$N$4,0))*$E13 -> 29790.303 | Q13: =INDEX('Monthly Engine'!$C$60:$N$60,MATCH($D13,'Monthly Engine'!$C$4:$N$4,0))*$E13 -> -25989.697
A14: F10 | B14: 46267 | C14: 46273 | D14: Sep-26 | E14: 0.25 | F14: =INDEX('Monthly Engine'!$C$13:$N$13,MATCH($D14,'Monthly Engine'!$C$4:$N$4,0))*$E14 -> 44.532032 | G14: =INDEX('Monthly Engine'!$C$14:$N$14,MATCH($D14,'Monthly Engine'!$C$4:$N$4,0))*$E14 -> 11.106597 | H14: =INDEX('Monthly Engine'!$C$28:$N$28,MATCH($D14,'Monthly Engine'!$C$4:$N$4,0))*$E14 -> 93.064027 | I14: =(INDEX('Monthly Engine'!$C$31:$N$31,MATCH($D14,'Monthly Engine'!$C$4:$N$4,0))+INDEX('Monthly Engine'!$C$33:$N$33,MATCH($D14,'Monthly Engine'!$C$4:$N$4,0)))*$E14 -> 60.0625 | J14: =H14+I14 -> 153.12653 | K14: =INDEX('Monthly Engine'!$C$29:$N$29,MATCH($D14,'Monthly Engine'!$C$4:$N$4,0)) -> 847.33831 | L14: =INDEX('Monthly Engine'!$C$35:$N$35,MATCH($D14,'Monthly Engine'!$C$4:$N$4,0))*$E14 -> 110747.97 | M14: =INDEX('Monthly Engine'!$C$39:$N$39,MATCH($D14,'Monthly Engine'!$C$4:$N$4,0))*$E14 -> 896.15474 | N14: =INDEX('Monthly Engine'!$C$40:$N$40,MATCH($D14,'Monthly Engine'!$C$4:$N$4,0))/4 -> 12000 | O14: =N14-M14 -> 11103.845 | P14: =INDEX('Monthly Engine'!$C$50:$N$50,MATCH($D14,'Monthly Engine'!$C$4:$N$4,0))*$E14 -> 53918.124 | Q14: =INDEX('Monthly Engine'!$C$60:$N$60,MATCH($D14,'Monthly Engine'!$C$4:$N$4,0))*$E14 -> -27353.751
A15: F11 | B15: 46274 | C15: 46280 | D15: Sep-26 | E15: 0.25 | F15: =INDEX('Monthly Engine'!$C$13:$N$13,MATCH($D15,'Monthly Engine'!$C$4:$N$4,0))*$E15 -> 44.532032 | G15: =INDEX('Monthly Engine'!$C$14:$N$14,MATCH($D15,'Monthly Engine'!$C$4:$N$4,0))*$E15 -> 11.106597 | H15: =INDEX('Monthly Engine'!$C$28:$N$28,MATCH($D15,'Monthly Engine'!$C$4:$N$4,0))*$E15 -> 93.064027 | I15: =(INDEX('Monthly Engine'!$C$31:$N$31,MATCH($D15,'Monthly Engine'!$C$4:$N$4,0))+INDEX('Monthly Engine'!$C$33:$N$33,MATCH($D15,'Monthly Engine'!$C$4:$N$4,0)))*$E15 -> 60.0625 | J15: =H15+I15 -> 153.12653 | K15: =INDEX('Monthly Engine'!$C$29:$N$29,MATCH($D15,'Monthly Engine'!$C$4:$N$4,0)) -> 847.33831 | L15: =INDEX('Monthly Engine'!$C$35:$N$35,MATCH($D15,'Monthly Engine'!$C$4:$N$4,0))*$E15 -> 110747.97 | M15: =INDEX('Monthly Engine'!$C$39:$N$39,MATCH($D15,'Monthly Engine'!$C$4:$N$4,0))*$E15 -> 896.15474 | N15: =INDEX('Monthly Engine'!$C$40:$N$40,MATCH($D15,'Monthly Engine'!$C$4:$N$4,0))/4 -> 12000 | O15: =N15-M15 -> 11103.845 | P15: =INDEX('Monthly Engine'!$C$50:$N$50,MATCH($D15,'Monthly Engine'!$C$4:$N$4,0))*$E15 -> 53918.124 | Q15: =INDEX('Monthly Engine'!$C$60:$N$60,MATCH($D15,'Monthly Engine'!$C$4:$N$4,0))*$E15 -> -27353.751
A16: F12 | B16: 46281 | C16: 46287 | D16: Sep-26 | E16: 0.25 | F16: =INDEX('Monthly Engine'!$C$13:$N$13,MATCH($D16,'Monthly Engine'!$C$4:$N$4,0))*$E16 -> 44.532032 | G16: =INDEX('Monthly Engine'!$C$14:$N$14,MATCH($D16,'Monthly Engine'!$C$4:$N$4,0))*$E16 -> 11.106597 | H16: =INDEX('Monthly Engine'!$C$28:$N$28,MATCH($D16,'Monthly Engine'!$C$4:$N$4,0))*$E16 -> 93.064027 | I16: =(INDEX('Monthly Engine'!$C$31:$N$31,MATCH($D16,'Monthly Engine'!$C$4:$N$4,0))+INDEX('Monthly Engine'!$C$33:$N$33,MATCH($D16,'Monthly Engine'!$C$4:$N$4,0)))*$E16 -> 60.0625 | J16: =H16+I16 -> 153.12653 | K16: =INDEX('Monthly Engine'!$C$29:$N$29,MATCH($D16,'Monthly Engine'!$C$4:$N$4,0)) -> 847.33831 | L16: =INDEX('Monthly Engine'!$C$35:$N$35,MATCH($D16,'Monthly Engine'!$C$4:$N$4,0))*$E16 -> 110747.97 | M16: =INDEX('Monthly Engine'!$C$39:$N$39,MATCH($D16,'Monthly Engine'!$C$4:$N$4,0))*$E16 -> 896.15474 | N16: =INDEX('Monthly Engine'!$C$40:$N$40,MATCH($D16,'Monthly Engine'!$C$4:$N$4,0))/4 -> 12000 | O16: =N16-M16 -> 11103.845 | P16: =INDEX('Monthly Engine'!$C$50:$N$50,MATCH($D16,'Monthly Engine'!$C$4:$N$4,0))*$E16 -> 53918.124 | Q16: =INDEX('Monthly Engine'!$C$60:$N$60,MATCH($D16,'Monthly Engine'!$C$4:$N$4,0))*$E16 -> -27353.751
A17: F13 | B17: 46288 | C17: 46294 | D17: Sep-26 | E17: 0.25 | F17: =INDEX('Monthly Engine'!$C$13:$N$13,MATCH($D17,'Monthly Engine'!$C$4:$N$4,0))*$E17 -> 44.532032 | G17: =INDEX('Monthly Engine'!$C$14:$N$14,MATCH($D17,'Monthly Engine'!$C$4:$N$4,0))*$E17 -> 11.106597 | H17: =INDEX('Monthly Engine'!$C$28:$N$28,MATCH($D17,'Monthly Engine'!$C$4:$N$4,0))*$E17 -> 93.064027 | I17: =(INDEX('Monthly Engine'!$C$31:$N$31,MATCH($D17,'Monthly Engine'!$C$4:$N$4,0))+INDEX('Monthly Engine'!$C$33:$N$33,MATCH($D17,'Monthly Engine'!$C$4:$N$4,0)))*$E17 -> 60.0625 | J17: =H17+I17 -> 153.12653 | K17: =INDEX('Monthly Engine'!$C$29:$N$29,MATCH($D17,'Monthly Engine'!$C$4:$N$4,0)) -> 847.33831 | L17: =INDEX('Monthly Engine'!$C$35:$N$35,MATCH($D17,'Monthly Engine'!$C$4:$N$4,0))*$E17 -> 110747.97 | M17: =INDEX('Monthly Engine'!$C$39:$N$39,MATCH($D17,'Monthly Engine'!$C$4:$N$4,0))*$E17 -> 896.15474 | N17: =INDEX('Monthly Engine'!$C$40:$N$40,MATCH($D17,'Monthly Engine'!$C$4:$N$4,0))/4 -> 12000 | O17: =N17-M17 -> 11103.845 | P17: =INDEX('Monthly Engine'!$C$50:$N$50,MATCH($D17,'Monthly Engine'!$C$4:$N$4,0))*$E17 -> 53918.124 | Q17: =INDEX('Monthly Engine'!$C$60:$N$60,MATCH($D17,'Monthly Engine'!$C$4:$N$4,0))*$E17 -> -27353.751
A18: F14 | B18: 46295 | C18: 46301 | D18: Oct-26 | E18: 0.2 | F18: =INDEX('Monthly Engine'!$C$13:$N$13,MATCH($D18,'Monthly Engine'!$C$4:$N$4,0))*$E18 -> 42.223599 | G18: =INDEX('Monthly Engine'!$C$14:$N$14,MATCH($D18,'Monthly Engine'!$C$4:$N$4,0))*$E18 -> 10.652417 | H18: =INDEX('Monthly Engine'!$C$28:$N$28,MATCH($D18,'Monthly Engine'!$C$4:$N$4,0))*$E18 -> 87.850536 | I18: =(INDEX('Monthly Engine'!$C$31:$N$31,MATCH($D18,'Monthly Engine'!$C$4:$N$4,0))+INDEX('Monthly Engine'!$C$33:$N$33,MATCH($D18,'Monthly Engine'!$C$4:$N$4,0)))*$E18 -> 89.675 | J18: =H18+I18 -> 177.52554 | K18: =INDEX('Monthly Engine'!$C$29:$N$29,MATCH($D18,'Monthly Engine'!$C$4:$N$4,0)) -> 856.65903 | L18: =INDEX('Monthly Engine'!$C$35:$N$35,MATCH($D18,'Monthly Engine'!$C$4:$N$4,0))*$E18 -> 121962.8 | M18: =INDEX('Monthly Engine'!$C$39:$N$39,MATCH($D18,'Monthly Engine'!$C$4:$N$4,0))*$E18 -> 1008.1288 | N18: =INDEX('Monthly Engine'!$C$40:$N$40,MATCH($D18,'Monthly Engine'!$C$4:$N$4,0))/5 -> 19200 | O18: =N18-M18 -> 18191.871 | P18: =INDEX('Monthly Engine'!$C$50:$N$50,MATCH($D18,'Monthly Engine'!$C$4:$N$4,0))*$E18 -> 58796.294 | Q18: =INDEX('Monthly Engine'!$C$60:$N$60,MATCH($D18,'Monthly Engine'!$C$4:$N$4,0))*$E18 -> -7519.0812
A19: F15 | B19: 46302 | C19: 46308 | D19: Oct-26 | E19: 0.2 | F19: =INDEX('Monthly Engine'!$C$13:$N$13,MATCH($D19,'Monthly Engine'!$C$4:$N$4,0))*$E19 -> 42.223599 | G19: =INDEX('Monthly Engine'!$C$14:$N$14,MATCH($D19,'Monthly Engine'!$C$4:$N$4,0))*$E19 -> 10.652417 | H19: =INDEX('Monthly Engine'!$C$28:$N$28,MATCH($D19,'Monthly Engine'!$C$4:$N$4,0))*$E19 -> 87.850536 | I19: =(INDEX('Monthly Engine'!$C$31:$N$31,MATCH($D19,'Monthly Engine'!$C$4:$N$4,0))+INDEX('Monthly Engine'!$C$33:$N$33,MATCH($D19,'Monthly Engine'!$C$4:$N$4,0)))*$E19 -> 89.675 | J19: =H19+I19 -> 177.52554 | K19: =INDEX('Monthly Engine'!$C$29:$N$29,MATCH($D19,'Monthly Engine'!$C$4:$N$4,0)) -> 856.65903 | L19: =INDEX('Monthly Engine'!$C$35:$N$35,MATCH($D19,'Monthly Engine'!$C$4:$N$4,0))*$E19 -> 121962.8 | M19: =INDEX('Monthly Engine'!$C$39:$N$39,MATCH($D19,'Monthly Engine'!$C$4:$N$4,0))*$E19 -> 1008.1288 | N19: =INDEX('Monthly Engine'!$C$40:$N$40,MATCH($D19,'Monthly Engine'!$C$4:$N$4,0))/5 -> 19200 | O19: =N19-M19 -> 18191.871 | P19: =INDEX('Monthly Engine'!$C$50:$N$50,MATCH($D19,'Monthly Engine'!$C$4:$N$4,0))*$E19 -> 58796.294 | Q19: =INDEX('Monthly Engine'!$C$60:$N$60,MATCH($D19,'Monthly Engine'!$C$4:$N$4,0))*$E19 -> -7519.0812
A20: F16 | B20: 46309 | C20: 46315 | D20: Oct-26 | E20: 0.2 | F20: =INDEX('Monthly Engine'!$C$13:$N$13,MATCH($D20,'Monthly Engine'!$C$4:$N$4,0))*$E20 -> 42.223599 | G20: =INDEX('Monthly Engine'!$C$14:$N$14,MATCH($D20,'Monthly Engine'!$C$4:$N$4,0))*$E20 -> 10.652417 | H20: =INDEX('Monthly Engine'!$C$28:$N$28,MATCH($D20,'Monthly Engine'!$C$4:$N$4,0))*$E20 -> 87.850536 | I20: =(INDEX('Monthly Engine'!$C$31:$N$31,MATCH($D20,'Monthly Engine'!$C$4:$N$4,0))+INDEX('Monthly Engine'!$C$33:$N$33,MATCH($D20,'Monthly Engine'!$C$4:$N$4,0)))*$E20 -> 89.675 | J20: =H20+I20 -> 177.52554 | K20: =INDEX('Monthly Engine'!$C$29:$N$29,MATCH($D20,'Monthly Engine'!$C$4:$N$4,0)) -> 856.65903 | L20: =INDEX('Monthly Engine'!$C$35:$N$35,MATCH($D20,'Monthly Engine'!$C$4:$N$4,0))*$E20 -> 121962.8 | M20: =INDEX('Monthly Engine'!$C$39:$N$39,MATCH($D20,'Monthly Engine'!$C$4:$N$4,0))*$E20 -> 1008.1288 | N20: =INDEX('Monthly Engine'!$C$40:$N$40,MATCH($D20,'Monthly Engine'!$C$4:$N$4,0))/5 -> 19200 | O20: =N20-M20 -> 18191.871 | P20: =INDEX('Monthly Engine'!$C$50:$N$50,MATCH($D20,'Monthly Engine'!$C$4:$N$4,0))*$E20 -> 58796.294 | Q20: =INDEX('Monthly Engine'!$C$60:$N$60,MATCH($D20,'Monthly Engine'!$C$4:$N$4,0))*$E20 -> -7519.0812
A21: F17 | B21: 46316 | C21: 46322 | D21: Oct-26 | E21: 0.2 | F21: =INDEX('Monthly Engine'!$C$13:$N$13,MATCH($D21,'Monthly Engine'!$C$4:$N$4,0))*$E21 -> 42.223599 | G21: =INDEX('Monthly Engine'!$C$14:$N$14,MATCH($D21,'Monthly Engine'!$C$4:$N$4,0))*$E21 -> 10.652417 | H21: =INDEX('Monthly Engine'!$C$28:$N$28,MATCH($D21,'Monthly Engine'!$C$4:$N$4,0))*$E21 -> 87.850536 | I21: =(INDEX('Monthly Engine'!$C$31:$N$31,MATCH($D21,'Monthly Engine'!$C$4:$N$4,0))+INDEX('Monthly Engine'!$C$33:$N$33,MATCH($D21,'Monthly Engine'!$C$4:$N$4,0)))*$E21 -> 89.675 | J21: =H21+I21 -> 177.52554 | K21: =INDEX('Monthly Engine'!$C$29:$N$29,MATCH($D21,'Monthly Engine'!$C$4:$N$4,0)) -> 856.65903 | L21: =INDEX('Monthly Engine'!$C$35:$N$35,MATCH($D21,'Monthly Engine'!$C$4:$N$4,0))*$E21 -> 121962.8 | M21: =INDEX('Monthly Engine'!$C$39:$N$39,MATCH($D21,'Monthly Engine'!$C$4:$N$4,0))*$E21 -> 1008.1288 | N21: =INDEX('Monthly Engine'!$C$40:$N$40,MATCH($D21,'Monthly Engine'!$C$4:$N$4,0))/5 -> 19200 | O21: =N21-M21 -> 18191.871 | P21: =INDEX('Monthly Engine'!$C$50:$N$50,MATCH($D21,'Monthly Engine'!$C$4:$N$4,0))*$E21 -> 58796.294 | Q21: =INDEX('Monthly Engine'!$C$60:$N$60,MATCH($D21,'Monthly Engine'!$C$4:$N$4,0))*$E21 -> -7519.0812
A22: F18 | B22: 46323 | C22: 46329 | D22: Oct-26 | E22: 0.2 | F22: =INDEX('Monthly Engine'!$C$13:$N$13,MATCH($D22,'Monthly Engine'!$C$4:$N$4,0))*$E22 -> 42.223599 | G22: =INDEX('Monthly Engine'!$C$14:$N$14,MATCH($D22,'Monthly Engine'!$C$4:$N$4,0))*$E22 -> 10.652417 | H22: =INDEX('Monthly Engine'!$C$28:$N$28,MATCH($D22,'Monthly Engine'!$C$4:$N$4,0))*$E22 -> 87.850536 | I22: =(INDEX('Monthly Engine'!$C$31:$N$31,MATCH($D22,'Monthly Engine'!$C$4:$N$4,0))+INDEX('Monthly Engine'!$C$33:$N$33,MATCH($D22,'Monthly Engine'!$C$4:$N$4,0)))*$E22 -> 89.675 | J22: =H22+I22 -> 177.52554 | K22: =INDEX('Monthly Engine'!$C$29:$N$29,MATCH($D22,'Monthly Engine'!$C$4:$N$4,0)) -> 856.65903 | L22: =INDEX('Monthly Engine'!$C$35:$N$35,MATCH($D22,'Monthly Engine'!$C$4:$N$4,0))*$E22 -> 121962.8 | M22: =INDEX('Monthly Engine'!$C$39:$N$39,MATCH($D22,'Monthly Engine'!$C$4:$N$4,0))*$E22 -> 1008.1288 | N22: =INDEX('Monthly Engine'!$C$40:$N$40,MATCH($D22,'Monthly Engine'!$C$4:$N$4,0))/5 -> 19200 | O22: =N22-M22 -> 18191.871 | P22: =INDEX('Monthly Engine'!$C$50:$N$50,MATCH($D22,'Monthly Engine'!$C$4:$N$4,0))*$E22 -> 58796.294 | Q22: =INDEX('Monthly Engine'!$C$60:$N$60,MATCH($D22,'Monthly Engine'!$C$4:$N$4,0))*$E22 -> -7519.0812
A23: F19 | B23: 46330 | C23: 46336 | D23: Nov-26 | E23: 0.375 | F23: =INDEX('Monthly Engine'!$C$13:$N$13,MATCH($D23,'Monthly Engine'!$C$4:$N$4,0))*$E23 -> 79.970069 | G23: =INDEX('Monthly Engine'!$C$14:$N$14,MATCH($D23,'Monthly Engine'!$C$4:$N$4,0))*$E23 -> 22.475834 | H23: =INDEX('Monthly Engine'!$C$28:$N$28,MATCH($D23,'Monthly Engine'!$C$4:$N$4,0))*$E23 -> 181.05667 | I23: =(INDEX('Monthly Engine'!$C$31:$N$31,MATCH($D23,'Monthly Engine'!$C$4:$N$4,0))+INDEX('Monthly Engine'!$C$33:$N$33,MATCH($D23,'Monthly Engine'!$C$4:$N$4,0)))*$E23 -> 226.3125 | J23: =H23+I23 -> 407.36917 | K23: =INDEX('Monthly Engine'!$C$29:$N$29,MATCH($D23,'Monthly Engine'!$C$4:$N$4,0)) -> 866.08228 | L23: =INDEX('Monthly Engine'!$C$35:$N$35,MATCH($D23,'Monthly Engine'!$C$4:$N$4,0))*$E23 -> 273676.48 | M23: =INDEX('Monthly Engine'!$C$39:$N$39,MATCH($D23,'Monthly Engine'!$C$4:$N$4,0))*$E23 -> 2287.3194 | N23: =INDEX('Monthly Engine'!$C$40:$N$40,MATCH($D23,'Monthly Engine'!$C$4:$N$4,0))/4 -> 24000 | O23: =N23-M23 -> 21712.681 | P23: =INDEX('Monthly Engine'!$C$50:$N$50,MATCH($D23,'Monthly Engine'!$C$4:$N$4,0))*$E23 -> 131928.38 | Q23: =INDEX('Monthly Engine'!$C$60:$N$60,MATCH($D23,'Monthly Engine'!$C$4:$N$4,0))*$E23 -> 5034.6772 | R23: Diwali week (demand nudge)
A24: F20 | B24: 46337 | C24: 46343 | D24: Nov-26 | E24: 0.2083 | F24: =INDEX('Monthly Engine'!$C$13:$N$13,MATCH($D24,'Monthly Engine'!$C$4:$N$4,0))*$E24 -> 44.420708 | G24: =INDEX('Monthly Engine'!$C$14:$N$14,MATCH($D24,'Monthly Engine'!$C$4:$N$4,0))*$E24 -> 12.484577 | H24: =INDEX('Monthly Engine'!$C$28:$N$28,MATCH($D24,'Monthly Engine'!$C$4:$N$4,0))*$E24 -> 100.57095 | I24: =(INDEX('Monthly Engine'!$C$31:$N$31,MATCH($D24,'Monthly Engine'!$C$4:$N$4,0))+INDEX('Monthly Engine'!$C$33:$N$33,MATCH($D24,'Monthly Engine'!$C$4:$N$4,0)))*$E24 -> 125.70905 | J24: =H24+I24 -> 226.28 | K24: =INDEX('Monthly Engine'!$C$29:$N$29,MATCH($D24,'Monthly Engine'!$C$4:$N$4,0)) -> 866.08228 | L24: =INDEX('Monthly Engine'!$C$35:$N$35,MATCH($D24,'Monthly Engine'!$C$4:$N$4,0))*$E24 -> 152018.16 | M24: =INDEX('Monthly Engine'!$C$39:$N$39,MATCH($D24,'Monthly Engine'!$C$4:$N$4,0))*$E24 -> 1270.5297 | N24: =INDEX('Monthly Engine'!$C$40:$N$40,MATCH($D24,'Monthly Engine'!$C$4:$N$4,0))/4 -> 24000 | O24: =N24-M24 -> 22729.47 | P24: =INDEX('Monthly Engine'!$C$50:$N$50,MATCH($D24,'Monthly Engine'!$C$4:$N$4,0))*$E24 -> 73281.82 | Q24: =INDEX('Monthly Engine'!$C$60:$N$60,MATCH($D24,'Monthly Engine'!$C$4:$N$4,0))*$E24 -> 2796.5954
A25: F21 | B25: 46344 | C25: 46350 | D25: Nov-26 | E25: 0.2083 | F25: =INDEX('Monthly Engine'!$C$13:$N$13,MATCH($D25,'Monthly Engine'!$C$4:$N$4,0))*$E25 -> 44.420708 | G25: =INDEX('Monthly Engine'!$C$14:$N$14,MATCH($D25,'Monthly Engine'!$C$4:$N$4,0))*$E25 -> 12.484577 | H25: =INDEX('Monthly Engine'!$C$28:$N$28,MATCH($D25,'Monthly Engine'!$C$4:$N$4,0))*$E25 -> 100.57095 | I25: =(INDEX('Monthly Engine'!$C$31:$N$31,MATCH($D25,'Monthly Engine'!$C$4:$N$4,0))+INDEX('Monthly Engine'!$C$33:$N$33,MATCH($D25,'Monthly Engine'!$C$4:$N$4,0)))*$E25 -> 125.70905 | J25: =H25+I25 -> 226.28 | K25: =INDEX('Monthly Engine'!$C$29:$N$29,MATCH($D25,'Monthly Engine'!$C$4:$N$4,0)) -> 866.08228 | L25: =INDEX('Monthly Engine'!$C$35:$N$35,MATCH($D25,'Monthly Engine'!$C$4:$N$4,0))*$E25 -> 152018.16 | M25: =INDEX('Monthly Engine'!$C$39:$N$39,MATCH($D25,'Monthly Engine'!$C$4:$N$4,0))*$E25 -> 1270.5297 | N25: =INDEX('Monthly Engine'!$C$40:$N$40,MATCH($D25,'Monthly Engine'!$C$4:$N$4,0))/4 -> 24000 | O25: =N25-M25 -> 22729.47 | P25: =INDEX('Monthly Engine'!$C$50:$N$50,MATCH($D25,'Monthly Engine'!$C$4:$N$4,0))*$E25 -> 73281.82 | Q25: =INDEX('Monthly Engine'!$C$60:$N$60,MATCH($D25,'Monthly Engine'!$C$4:$N$4,0))*$E25 -> 2796.5954
A26: F22 | B26: 46351 | C26: 46357 | D26: Nov-26 | E26: 0.2083 | F26: =INDEX('Monthly Engine'!$C$13:$N$13,MATCH($D26,'Monthly Engine'!$C$4:$N$4,0))*$E26 -> 44.420708 | G26: =INDEX('Monthly Engine'!$C$14:$N$14,MATCH($D26,'Monthly Engine'!$C$4:$N$4,0))*$E26 -> 12.484577 | H26: =INDEX('Monthly Engine'!$C$28:$N$28,MATCH($D26,'Monthly Engine'!$C$4:$N$4,0))*$E26 -> 100.57095 | I26: =(INDEX('Monthly Engine'!$C$31:$N$31,MATCH($D26,'Monthly Engine'!$C$4:$N$4,0))+INDEX('Monthly Engine'!$C$33:$N$33,MATCH($D26,'Monthly Engine'!$C$4:$N$4,0)))*$E26 -> 125.70905 | J26: =H26+I26 -> 226.28 | K26: =INDEX('Monthly Engine'!$C$29:$N$29,MATCH($D26,'Monthly Engine'!$C$4:$N$4,0)) -> 866.08228 | L26: =INDEX('Monthly Engine'!$C$35:$N$35,MATCH($D26,'Monthly Engine'!$C$4:$N$4,0))*$E26 -> 152018.16 | M26: =INDEX('Monthly Engine'!$C$39:$N$39,MATCH($D26,'Monthly Engine'!$C$4:$N$4,0))*$E26 -> 1270.5297 | N26: =INDEX('Monthly Engine'!$C$40:$N$40,MATCH($D26,'Monthly Engine'!$C$4:$N$4,0))/4 -> 24000 | O26: =N26-M26 -> 22729.47 | P26: =INDEX('Monthly Engine'!$C$50:$N$50,MATCH($D26,'Monthly Engine'!$C$4:$N$4,0))*$E26 -> 73281.82 | Q26: =INDEX('Monthly Engine'!$C$60:$N$60,MATCH($D26,'Monthly Engine'!$C$4:$N$4,0))*$E26 -> 2796.5954
A27: F23 | B27: 46358 | C27: 46364 | D27: Dec-26 | E27: 0.25 | F27: =INDEX('Monthly Engine'!$C$13:$N$13,MATCH($D27,'Monthly Engine'!$C$4:$N$4,0))*$E27 -> 47.236247 | G27: =INDEX('Monthly Engine'!$C$14:$N$14,MATCH($D27,'Monthly Engine'!$C$4:$N$4,0))*$E27 -> 16.088921 | H27: =INDEX('Monthly Engine'!$C$28:$N$28,MATCH($D27,'Monthly Engine'!$C$4:$N$4,0))*$E27 -> 123.24258 | I27: =(INDEX('Monthly Engine'!$C$31:$N$31,MATCH($D27,'Monthly Engine'!$C$4:$N$4,0))+INDEX('Monthly Engine'!$C$33:$N$33,MATCH($D27,'Monthly Engine'!$C$4:$N$4,0)))*$E27 -> 163.98958 | J27: =H27+I27 -> 287.23216 | K27: =INDEX('Monthly Engine'!$C$29:$N$29,MATCH($D27,'Monthly Engine'!$C$4:$N$4,0)) -> 875.60918 | L27: =INDEX('Monthly Engine'!$C$35:$N$35,MATCH($D27,'Monthly Engine'!$C$4:$N$4,0))*$E27 -> 192188.56 | M27: =INDEX('Monthly Engine'!$C$39:$N$39,MATCH($D27,'Monthly Engine'!$C$4:$N$4,0))*$E27 -> 1614.7238 | N27: =INDEX('Monthly Engine'!$C$40:$N$40,MATCH($D27,'Monthly Engine'!$C$4:$N$4,0))/4 -> 24000 | O27: =N27-M27 -> 22385.276 | P27: =INDEX('Monthly Engine'!$C$50:$N$50,MATCH($D27,'Monthly Engine'!$C$4:$N$4,0))*$E27 -> 93179.891 | Q27: =INDEX('Monthly Engine'!$C$60:$N$60,MATCH($D27,'Monthly Engine'!$C$4:$N$4,0))*$E27 -> -1950.7038
A28: F24 | B28: 46365 | C28: 46371 | D28: Dec-26 | E28: 0.25 | F28: =INDEX('Monthly Engine'!$C$13:$N$13,MATCH($D28,'Monthly Engine'!$C$4:$N$4,0))*$E28 -> 47.236247 | G28: =INDEX('Monthly Engine'!$C$14:$N$14,MATCH($D28,'Monthly Engine'!$C$4:$N$4,0))*$E28 -> 16.088921 | H28: =INDEX('Monthly Engine'!$C$28:$N$28,MATCH($D28,'Monthly Engine'!$C$4:$N$4,0))*$E28 -> 123.24258 | I28: =(INDEX('Monthly Engine'!$C$31:$N$31,MATCH($D28,'Monthly Engine'!$C$4:$N$4,0))+INDEX('Monthly Engine'!$C$33:$N$33,MATCH($D28,'Monthly Engine'!$C$4:$N$4,0)))*$E28 -> 163.98958 | J28: =H28+I28 -> 287.23216 | K28: =INDEX('Monthly Engine'!$C$29:$N$29,MATCH($D28,'Monthly Engine'!$C$4:$N$4,0)) -> 875.60918 | L28: =INDEX('Monthly Engine'!$C$35:$N$35,MATCH($D28,'Monthly Engine'!$C$4:$N$4,0))*$E28 -> 192188.56 | M28: =INDEX('Monthly Engine'!$C$39:$N$39,MATCH($D28,'Monthly Engine'!$C$4:$N$4,0))*$E28 -> 1614.7238 | N28: =INDEX('Monthly Engine'!$C$40:$N$40,MATCH($D28,'Monthly Engine'!$C$4:$N$4,0))/4 -> 24000 | O28: =N28-M28 -> 22385.276 | P28: =INDEX('Monthly Engine'!$C$50:$N$50,MATCH($D28,'Monthly Engine'!$C$4:$N$4,0))*$E28 -> 93179.891 | Q28: =INDEX('Monthly Engine'!$C$60:$N$60,MATCH($D28,'Monthly Engine'!$C$4:$N$4,0))*$E28 -> -1950.7038
A29: F25 | B29: 46372 | C29: 46378 | D29: Dec-26 | E29: 0.25 | F29: =INDEX('Monthly Engine'!$C$13:$N$13,MATCH($D29,'Monthly Engine'!$C$4:$N$4,0))*$E29 -> 47.236247 | G29: =INDEX('Monthly Engine'!$C$14:$N$14,MATCH($D29,'Monthly Engine'!$C$4:$N$4,0))*$E29 -> 16.088921 | H29: =INDEX('Monthly Engine'!$C$28:$N$28,MATCH($D29,'Monthly Engine'!$C$4:$N$4,0))*$E29 -> 123.24258 | I29: =(INDEX('Monthly Engine'!$C$31:$N$31,MATCH($D29,'Monthly Engine'!$C$4:$N$4,0))+INDEX('Monthly Engine'!$C$33:$N$33,MATCH($D29,'Monthly Engine'!$C$4:$N$4,0)))*$E29 -> 163.98958 | J29: =H29+I29 -> 287.23216 | K29: =INDEX('Monthly Engine'!$C$29:$N$29,MATCH($D29,'Monthly Engine'!$C$4:$N$4,0)) -> 875.60918 | L29: =INDEX('Monthly Engine'!$C$35:$N$35,MATCH($D29,'Monthly Engine'!$C$4:$N$4,0))*$E29 -> 192188.56 | M29: =INDEX('Monthly Engine'!$C$39:$N$39,MATCH($D29,'Monthly Engine'!$C$4:$N$4,0))*$E29 -> 1614.7238 | N29: =INDEX('Monthly Engine'!$C$40:$N$40,MATCH($D29,'Monthly Engine'!$C$4:$N$4,0))/4 -> 24000 | O29: =N29-M29 -> 22385.276 | P29: =INDEX('Monthly Engine'!$C$50:$N$50,MATCH($D29,'Monthly Engine'!$C$4:$N$4,0))*$E29 -> 93179.891 | Q29: =INDEX('Monthly Engine'!$C$60:$N$60,MATCH($D29,'Monthly Engine'!$C$4:$N$4,0))*$E29 -> -1950.7038
A30: F26 | B30: 46379 | C30: 46385 | D30: Dec-26 | E30: 0.25 | F30: =INDEX('Monthly Engine'!$C$13:$N$13,MATCH($D30,'Monthly Engine'!$C$4:$N$4,0))*$E30 -> 47.236247 | G30: =INDEX('Monthly Engine'!$C$14:$N$14,MATCH($D30,'Monthly Engine'!$C$4:$N$4,0))*$E30 -> 16.088921 | H30: =INDEX('Monthly Engine'!$C$28:$N$28,MATCH($D30,'Monthly Engine'!$C$4:$N$4,0))*$E30 -> 123.24258 | I30: =(INDEX('Monthly Engine'!$C$31:$N$31,MATCH($D30,'Monthly Engine'!$C$4:$N$4,0))+INDEX('Monthly Engine'!$C$33:$N$33,MATCH($D30,'Monthly Engine'!$C$4:$N$4,0)))*$E30 -> 163.98958 | J30: =H30+I30 -> 287.23216 | K30: =INDEX('Monthly Engine'!$C$29:$N$29,MATCH($D30,'Monthly Engine'!$C$4:$N$4,0)) -> 875.60918 | L30: =INDEX('Monthly Engine'!$C$35:$N$35,MATCH($D30,'Monthly Engine'!$C$4:$N$4,0))*$E30 -> 192188.56 | M30: =INDEX('Monthly Engine'!$C$39:$N$39,MATCH($D30,'Monthly Engine'!$C$4:$N$4,0))*$E30 -> 1614.7238 | N30: =INDEX('Monthly Engine'!$C$40:$N$40,MATCH($D30,'Monthly Engine'!$C$4:$N$4,0))/4 -> 24000 | O30: =N30-M30 -> 22385.276 | P30: =INDEX('Monthly Engine'!$C$50:$N$50,MATCH($D30,'Monthly Engine'!$C$4:$N$4,0))*$E30 -> 93179.891 | Q30: =INDEX('Monthly Engine'!$C$60:$N$60,MATCH($D30,'Monthly Engine'!$C$4:$N$4,0))*$E30 -> -1950.7038
A31: F27 | B31: 46386 | C31: 46392 | D31: Jan-27 | E31: 0.3 | F31: =INDEX('Monthly Engine'!$C$13:$N$13,MATCH($D31,'Monthly Engine'!$C$4:$N$4,0))*$E31 -> 61.617812 | G31: =INDEX('Monthly Engine'!$C$14:$N$14,MATCH($D31,'Monthly Engine'!$C$4:$N$4,0))*$E31 -> 21.653181 | H31: =INDEX('Monthly Engine'!$C$28:$N$28,MATCH($D31,'Monthly Engine'!$C$4:$N$4,0))*$E31 -> 161.92875 | I31: =(INDEX('Monthly Engine'!$C$31:$N$31,MATCH($D31,'Monthly Engine'!$C$4:$N$4,0))+INDEX('Monthly Engine'!$C$33:$N$33,MATCH($D31,'Monthly Engine'!$C$4:$N$4,0)))*$E31 -> 249.75 | J31: =H31+I31 -> 411.67875 | K31: =INDEX('Monthly Engine'!$C$29:$N$29,MATCH($D31,'Monthly Engine'!$C$4:$N$4,0)) -> 885.24089 | L31: =INDEX('Monthly Engine'!$C$35:$N$35,MATCH($D31,'Monthly Engine'!$C$4:$N$4,0))*$E31 -> 271298.95 | M31: =INDEX('Monthly Engine'!$C$39:$N$39,MATCH($D31,'Monthly Engine'!$C$4:$N$4,0))*$E31 -> 2298.7379 | N31: =INDEX('Monthly Engine'!$C$40:$N$40,MATCH($D31,'Monthly Engine'!$C$4:$N$4,0))/5 -> 19200 | O31: =N31-M31 -> 16901.262 | P31: =INDEX('Monthly Engine'!$C$50:$N$50,MATCH($D31,'Monthly Engine'!$C$4:$N$4,0))*$E31 -> 131889.67 | Q31: =INDEX('Monthly Engine'!$C$60:$N$60,MATCH($D31,'Monthly Engine'!$C$4:$N$4,0))*$E31 -> 15486.374 | R31: New Year / gut-health resolution week (demand nudge)
A32: F28 | B32: 46393 | C32: 46399 | D32: Jan-27 | E32: 0.175 | F32: =INDEX('Monthly Engine'!$C$13:$N$13,MATCH($D32,'Monthly Engine'!$C$4:$N$4,0))*$E32 -> 35.943723 | G32: =INDEX('Monthly Engine'!$C$14:$N$14,MATCH($D32,'Monthly Engine'!$C$4:$N$4,0))*$E32 -> 12.631022 | H32: =INDEX('Monthly Engine'!$C$28:$N$28,MATCH($D32,'Monthly Engine'!$C$4:$N$4,0))*$E32 -> 94.458436 | I32: =(INDEX('Monthly Engine'!$C$31:$N$31,MATCH($D32,'Monthly Engine'!$C$4:$N$4,0))+INDEX('Monthly Engine'!$C$33:$N$33,MATCH($D32,'Monthly Engine'!$C$4:$N$4,0)))*$E32 -> 145.6875 | J32: =H32+I32 -> 240.14594 | K32: =INDEX('Monthly Engine'!$C$29:$N$29,MATCH($D32,'Monthly Engine'!$C$4:$N$4,0)) -> 885.24089 | L32: =INDEX('Monthly Engine'!$C$35:$N$35,MATCH($D32,'Monthly Engine'!$C$4:$N$4,0))*$E32 -> 158257.72 | M32: =INDEX('Monthly Engine'!$C$39:$N$39,MATCH($D32,'Monthly Engine'!$C$4:$N$4,0))*$E32 -> 1340.9305 | N32: =INDEX('Monthly Engine'!$C$40:$N$40,MATCH($D32,'Monthly Engine'!$C$4:$N$4,0))/5 -> 19200 | O32: =N32-M32 -> 17859.07 | P32: =INDEX('Monthly Engine'!$C$50:$N$50,MATCH($D32,'Monthly Engine'!$C$4:$N$4,0))*$E32 -> 76935.643 | Q32: =INDEX('Monthly Engine'!$C$60:$N$60,MATCH($D32,'Monthly Engine'!$C$4:$N$4,0))*$E32 -> 9033.7184
A33: F29 | B33: 46400 | C33: 46406 | D33: Jan-27 | E33: 0.175 | F33: =INDEX('Monthly Engine'!$C$13:$N$13,MATCH($D33,'Monthly Engine'!$C$4:$N$4,0))*$E33 -> 35.943723 | G33: =INDEX('Monthly Engine'!$C$14:$N$14,MATCH($D33,'Monthly Engine'!$C$4:$N$4,0))*$E33 -> 12.631022 | H33: =INDEX('Monthly Engine'!$C$28:$N$28,MATCH($D33,'Monthly Engine'!$C$4:$N$4,0))*$E33 -> 94.458436 | I33: =(INDEX('Monthly Engine'!$C$31:$N$31,MATCH($D33,'Monthly Engine'!$C$4:$N$4,0))+INDEX('Monthly Engine'!$C$33:$N$33,MATCH($D33,'Monthly Engine'!$C$4:$N$4,0)))*$E33 -> 145.6875 | J33: =H33+I33 -> 240.14594 | K33: =INDEX('Monthly Engine'!$C$29:$N$29,MATCH($D33,'Monthly Engine'!$C$4:$N$4,0)) -> 885.24089 | L33: =INDEX('Monthly Engine'!$C$35:$N$35,MATCH($D33,'Monthly Engine'!$C$4:$N$4,0))*$E33 -> 158257.72 | M33: =INDEX('Monthly Engine'!$C$39:$N$39,MATCH($D33,'Monthly Engine'!$C$4:$N$4,0))*$E33 -> 1340.9305 | N33: =INDEX('Monthly Engine'!$C$40:$N$40,MATCH($D33,'Monthly Engine'!$C$4:$N$4,0))/5 -> 19200 | O33: =N33-M33 -> 17859.07 | P33: =INDEX('Monthly Engine'!$C$50:$N$50,MATCH($D33,'Monthly Engine'!$C$4:$N$4,0))*$E33 -> 76935.643 | Q33: =INDEX('Monthly Engine'!$C$60:$N$60,MATCH($D33,'Monthly Engine'!$C$4:$N$4,0))*$E33 -> 9033.7184
A34: F30 | B34: 46407 | C34: 46413 | D34: Jan-27 | E34: 0.175 | F34: =INDEX('Monthly Engine'!$C$13:$N$13,MATCH($D34,'Monthly Engine'!$C$4:$N$4,0))*$E34 -> 35.943723 | G34: =INDEX('Monthly Engine'!$C$14:$N$14,MATCH($D34,'Monthly Engine'!$C$4:$N$4,0))*$E34 -> 12.631022 | H34: =INDEX('Monthly Engine'!$C$28:$N$28,MATCH($D34,'Monthly Engine'!$C$4:$N$4,0))*$E34 -> 94.458436 | I34: =(INDEX('Monthly Engine'!$C$31:$N$31,MATCH($D34,'Monthly Engine'!$C$4:$N$4,0))+INDEX('Monthly Engine'!$C$33:$N$33,MATCH($D34,'Monthly Engine'!$C$4:$N$4,0)))*$E34 -> 145.6875 | J34: =H34+I34 -> 240.14594 | K34: =INDEX('Monthly Engine'!$C$29:$N$29,MATCH($D34,'Monthly Engine'!$C$4:$N$4,0)) -> 885.24089 | L34: =INDEX('Monthly Engine'!$C$35:$N$35,MATCH($D34,'Monthly Engine'!$C$4:$N$4,0))*$E34 -> 158257.72 | M34: =INDEX('Monthly Engine'!$C$39:$N$39,MATCH($D34,'Monthly Engine'!$C$4:$N$4,0))*$E34 -> 1340.9305 | N34: =INDEX('Monthly Engine'!$C$40:$N$40,MATCH($D34,'Monthly Engine'!$C$4:$N$4,0))/5 -> 19200 | O34: =N34-M34 -> 17859.07 | P34: =INDEX('Monthly Engine'!$C$50:$N$50,MATCH($D34,'Monthly Engine'!$C$4:$N$4,0))*$E34 -> 76935.643 | Q34: =INDEX('Monthly Engine'!$C$60:$N$60,MATCH($D34,'Monthly Engine'!$C$4:$N$4,0))*$E34 -> 9033.7184
A35: F31 | B35: 46414 | C35: 46420 | D35: Jan-27 | E35: 0.175 | F35: =INDEX('Monthly Engine'!$C$13:$N$13,MATCH($D35,'Monthly Engine'!$C$4:$N$4,0))*$E35 -> 35.943723 | G35: =INDEX('Monthly Engine'!$C$14:$N$14,MATCH($D35,'Monthly Engine'!$C$4:$N$4,0))*$E35 -> 12.631022 | H35: =INDEX('Monthly Engine'!$C$28:$N$28,MATCH($D35,'Monthly Engine'!$C$4:$N$4,0))*$E35 -> 94.458436 | I35: =(INDEX('Monthly Engine'!$C$31:$N$31,MATCH($D35,'Monthly Engine'!$C$4:$N$4,0))+INDEX('Monthly Engine'!$C$33:$N$33,MATCH($D35,'Monthly Engine'!$C$4:$N$4,0)))*$E35 -> 145.6875 | J35: =H35+I35 -> 240.14594 | K35: =INDEX('Monthly Engine'!$C$29:$N$29,MATCH($D35,'Monthly Engine'!$C$4:$N$4,0)) -> 885.24089 | L35: =INDEX('Monthly Engine'!$C$35:$N$35,MATCH($D35,'Monthly Engine'!$C$4:$N$4,0))*$E35 -> 158257.72 | M35: =INDEX('Monthly Engine'!$C$39:$N$39,MATCH($D35,'Monthly Engine'!$C$4:$N$4,0))*$E35 -> 1340.9305 | N35: =INDEX('Monthly Engine'!$C$40:$N$40,MATCH($D35,'Monthly Engine'!$C$4:$N$4,0))/5 -> 19200 | O35: =N35-M35 -> 17859.07 | P35: =INDEX('Monthly Engine'!$C$50:$N$50,MATCH($D35,'Monthly Engine'!$C$4:$N$4,0))*$E35 -> 76935.643 | Q35: =INDEX('Monthly Engine'!$C$60:$N$60,MATCH($D35,'Monthly Engine'!$C$4:$N$4,0))*$E35 -> 9033.7184
A36: F32 | B36: 46421 | C36: 46427 | D36: Feb-27 | E36: 0.25 | F36: =INDEX('Monthly Engine'!$C$13:$N$13,MATCH($D36,'Monthly Engine'!$C$4:$N$4,0))*$E36 -> 52.753226 | G36: =INDEX('Monthly Engine'!$C$14:$N$14,MATCH($D36,'Monthly Engine'!$C$4:$N$4,0))*$E36 -> 19.909183 | H36: =INDEX('Monthly Engine'!$C$28:$N$28,MATCH($D36,'Monthly Engine'!$C$4:$N$4,0))*$E36 -> 145.12536 | I36: =(INDEX('Monthly Engine'!$C$31:$N$31,MATCH($D36,'Monthly Engine'!$C$4:$N$4,0))+INDEX('Monthly Engine'!$C$33:$N$33,MATCH($D36,'Monthly Engine'!$C$4:$N$4,0)))*$E36 -> 241.53125 | J36: =H36+I36 -> 386.65661 | K36: =INDEX('Monthly Engine'!$C$29:$N$29,MATCH($D36,'Monthly Engine'!$C$4:$N$4,0)) -> 894.97854 | L36: =INDEX('Monthly Engine'!$C$35:$N$35,MATCH($D36,'Monthly Engine'!$C$4:$N$4,0))*$E36 -> 253360.02 | M36: =INDEX('Monthly Engine'!$C$39:$N$39,MATCH($D36,'Monthly Engine'!$C$4:$N$4,0))*$E36 -> 2158.3676 | N36: =INDEX('Monthly Engine'!$C$40:$N$40,MATCH($D36,'Monthly Engine'!$C$4:$N$4,0))/4 -> 24000 | O36: =N36-M36 -> 21841.632 | P36: =INDEX('Monthly Engine'!$C$50:$N$50,MATCH($D36,'Monthly Engine'!$C$4:$N$4,0))*$E36 -> 123872.53 | Q36: =INDEX('Monthly Engine'!$C$60:$N$60,MATCH($D36,'Monthly Engine'!$C$4:$N$4,0))*$E36 -> 24905.889
A37: F33 | B37: 46428 | C37: 46434 | D37: Feb-27 | E37: 0.25 | F37: =INDEX('Monthly Engine'!$C$13:$N$13,MATCH($D37,'Monthly Engine'!$C$4:$N$4,0))*$E37 -> 52.753226 | G37: =INDEX('Monthly Engine'!$C$14:$N$14,MATCH($D37,'Monthly Engine'!$C$4:$N$4,0))*$E37 -> 19.909183 | H37: =INDEX('Monthly Engine'!$C$28:$N$28,MATCH($D37,'Monthly Engine'!$C$4:$N$4,0))*$E37 -> 145.12536 | I37: =(INDEX('Monthly Engine'!$C$31:$N$31,MATCH($D37,'Monthly Engine'!$C$4:$N$4,0))+INDEX('Monthly Engine'!$C$33:$N$33,MATCH($D37,'Monthly Engine'!$C$4:$N$4,0)))*$E37 -> 241.53125 | J37: =H37+I37 -> 386.65661 | K37: =INDEX('Monthly Engine'!$C$29:$N$29,MATCH($D37,'Monthly Engine'!$C$4:$N$4,0)) -> 894.97854 | L37: =INDEX('Monthly Engine'!$C$35:$N$35,MATCH($D37,'Monthly Engine'!$C$4:$N$4,0))*$E37 -> 253360.02 | M37: =INDEX('Monthly Engine'!$C$39:$N$39,MATCH($D37,'Monthly Engine'!$C$4:$N$4,0))*$E37 -> 2158.3676 | N37: =INDEX('Monthly Engine'!$C$40:$N$40,MATCH($D37,'Monthly Engine'!$C$4:$N$4,0))/4 -> 24000 | O37: =N37-M37 -> 21841.632 | P37: =INDEX('Monthly Engine'!$C$50:$N$50,MATCH($D37,'Monthly Engine'!$C$4:$N$4,0))*$E37 -> 123872.53 | Q37: =INDEX('Monthly Engine'!$C$60:$N$60,MATCH($D37,'Monthly Engine'!$C$4:$N$4,0))*$E37 -> 24905.889
A38: F34 | B38: 46435 | C38: 46441 | D38: Feb-27 | E38: 0.25 | F38: =INDEX('Monthly Engine'!$C$13:$N$13,MATCH($D38,'Monthly Engine'!$C$4:$N$4,0))*$E38 -> 52.753226 | G38: =INDEX('Monthly Engine'!$C$14:$N$14,MATCH($D38,'Monthly Engine'!$C$4:$N$4,0))*$E38 -> 19.909183 | H38: =INDEX('Monthly Engine'!$C$28:$N$28,MATCH($D38,'Monthly Engine'!$C$4:$N$4,0))*$E38 -> 145.12536 | I38: =(INDEX('Monthly Engine'!$C$31:$N$31,MATCH($D38,'Monthly Engine'!$C$4:$N$4,0))+INDEX('Monthly Engine'!$C$33:$N$33,MATCH($D38,'Monthly Engine'!$C$4:$N$4,0)))*$E38 -> 241.53125 | J38: =H38+I38 -> 386.65661 | K38: =INDEX('Monthly Engine'!$C$29:$N$29,MATCH($D38,'Monthly Engine'!$C$4:$N$4,0)) -> 894.97854 | L38: =INDEX('Monthly Engine'!$C$35:$N$35,MATCH($D38,'Monthly Engine'!$C$4:$N$4,0))*$E38 -> 253360.02 | M38: =INDEX('Monthly Engine'!$C$39:$N$39,MATCH($D38,'Monthly Engine'!$C$4:$N$4,0))*$E38 -> 2158.3676 | N38: =INDEX('Monthly Engine'!$C$40:$N$40,MATCH($D38,'Monthly Engine'!$C$4:$N$4,0))/4 -> 24000 | O38: =N38-M38 -> 21841.632 | P38: =INDEX('Monthly Engine'!$C$50:$N$50,MATCH($D38,'Monthly Engine'!$C$4:$N$4,0))*$E38 -> 123872.53 | Q38: =INDEX('Monthly Engine'!$C$60:$N$60,MATCH($D38,'Monthly Engine'!$C$4:$N$4,0))*$E38 -> 24905.889
A39: F35 | B39: 46442 | C39: 46448 | D39: Feb-27 | E39: 0.25 | F39: =INDEX('Monthly Engine'!$C$13:$N$13,MATCH($D39,'Monthly Engine'!$C$4:$N$4,0))*$E39 -> 52.753226 | G39: =INDEX('Monthly Engine'!$C$14:$N$14,MATCH($D39,'Monthly Engine'!$C$4:$N$4,0))*$E39 -> 19.909183 | H39: =INDEX('Monthly Engine'!$C$28:$N$28,MATCH($D39,'Monthly Engine'!$C$4:$N$4,0))*$E39 -> 145.12536 | I39: =(INDEX('Monthly Engine'!$C$31:$N$31,MATCH($D39,'Monthly Engine'!$C$4:$N$4,0))+INDEX('Monthly Engine'!$C$33:$N$33,MATCH($D39,'Monthly Engine'!$C$4:$N$4,0)))*$E39 -> 241.53125 | J39: =H39+I39 -> 386.65661 | K39: =INDEX('Monthly Engine'!$C$29:$N$29,MATCH($D39,'Monthly Engine'!$C$4:$N$4,0)) -> 894.97854 | L39: =INDEX('Monthly Engine'!$C$35:$N$35,MATCH($D39,'Monthly Engine'!$C$4:$N$4,0))*$E39 -> 253360.02 | M39: =INDEX('Monthly Engine'!$C$39:$N$39,MATCH($D39,'Monthly Engine'!$C$4:$N$4,0))*$E39 -> 2158.3676 | N39: =INDEX('Monthly Engine'!$C$40:$N$40,MATCH($D39,'Monthly Engine'!$C$4:$N$4,0))/4 -> 24000 | O39: =N39-M39 -> 21841.632 | P39: =INDEX('Monthly Engine'!$C$50:$N$50,MATCH($D39,'Monthly Engine'!$C$4:$N$4,0))*$E39 -> 123872.53 | Q39: =INDEX('Monthly Engine'!$C$60:$N$60,MATCH($D39,'Monthly Engine'!$C$4:$N$4,0))*$E39 -> 24905.889
A40: F36 | B40: 46449 | C40: 46455 | D40: Mar-27 | E40: 0.25 | F40: =INDEX('Monthly Engine'!$C$13:$N$13,MATCH($D40,'Monthly Engine'!$C$4:$N$4,0))*$E40 -> 61.343029 | G40: =INDEX('Monthly Engine'!$C$14:$N$14,MATCH($D40,'Monthly Engine'!$C$4:$N$4,0))*$E40 -> 22.464563 | H40: =INDEX('Monthly Engine'!$C$28:$N$28,MATCH($D40,'Monthly Engine'!$C$4:$N$4,0))*$E40 -> 167.06399 | I40: =(INDEX('Monthly Engine'!$C$31:$N$31,MATCH($D40,'Monthly Engine'!$C$4:$N$4,0))+INDEX('Monthly Engine'!$C$33:$N$33,MATCH($D40,'Monthly Engine'!$C$4:$N$4,0)))*$E40 -> 309.86458 | J40: =H40+I40 -> 476.92857 | K40: =INDEX('Monthly Engine'!$C$29:$N$29,MATCH($D40,'Monthly Engine'!$C$4:$N$4,0)) -> 904.8233 | L40: =INDEX('Monthly Engine'!$C$35:$N$35,MATCH($D40,'Monthly Engine'!$C$4:$N$4,0))*$E40 -> 309321.56 | M40: =INDEX('Monthly Engine'!$C$39:$N$39,MATCH($D40,'Monthly Engine'!$C$4:$N$4,0))*$E40 -> 2651.5909 | N40: =INDEX('Monthly Engine'!$C$40:$N$40,MATCH($D40,'Monthly Engine'!$C$4:$N$4,0))/4 -> 24000 | O40: =N40-M40 -> 21348.409 | P40: =INDEX('Monthly Engine'!$C$50:$N$50,MATCH($D40,'Monthly Engine'!$C$4:$N$4,0))*$E40 -> 151968.56 | Q40: =INDEX('Monthly Engine'!$C$60:$N$60,MATCH($D40,'Monthly Engine'!$C$4:$N$4,0))*$E40 -> 40941.721
A41: F37 | B41: 46456 | C41: 46462 | D41: Mar-27 | E41: 0.25 | F41: =INDEX('Monthly Engine'!$C$13:$N$13,MATCH($D41,'Monthly Engine'!$C$4:$N$4,0))*$E41 -> 61.343029 | G41: =INDEX('Monthly Engine'!$C$14:$N$14,MATCH($D41,'Monthly Engine'!$C$4:$N$4,0))*$E41 -> 22.464563 | H41: =INDEX('Monthly Engine'!$C$28:$N$28,MATCH($D41,'Monthly Engine'!$C$4:$N$4,0))*$E41 -> 167.06399 | I41: =(INDEX('Monthly Engine'!$C$31:$N$31,MATCH($D41,'Monthly Engine'!$C$4:$N$4,0))+INDEX('Monthly Engine'!$C$33:$N$33,MATCH($D41,'Monthly Engine'!$C$4:$N$4,0)))*$E41 -> 309.86458 | J41: =H41+I41 -> 476.92857 | K41: =INDEX('Monthly Engine'!$C$29:$N$29,MATCH($D41,'Monthly Engine'!$C$4:$N$4,0)) -> 904.8233 | L41: =INDEX('Monthly Engine'!$C$35:$N$35,MATCH($D41,'Monthly Engine'!$C$4:$N$4,0))*$E41 -> 309321.56 | M41: =INDEX('Monthly Engine'!$C$39:$N$39,MATCH($D41,'Monthly Engine'!$C$4:$N$4,0))*$E41 -> 2651.5909 | N41: =INDEX('Monthly Engine'!$C$40:$N$40,MATCH($D41,'Monthly Engine'!$C$4:$N$4,0))/4 -> 24000 | O41: =N41-M41 -> 21348.409 | P41: =INDEX('Monthly Engine'!$C$50:$N$50,MATCH($D41,'Monthly Engine'!$C$4:$N$4,0))*$E41 -> 151968.56 | Q41: =INDEX('Monthly Engine'!$C$60:$N$60,MATCH($D41,'Monthly Engine'!$C$4:$N$4,0))*$E41 -> 40941.721
A42: F38 | B42: 46463 | C42: 46469 | D42: Mar-27 | E42: 0.25 | F42: =INDEX('Monthly Engine'!$C$13:$N$13,MATCH($D42,'Monthly Engine'!$C$4:$N$4,0))*$E42 -> 61.343029 | G42: =INDEX('Monthly Engine'!$C$14:$N$14,MATCH($D42,'Monthly Engine'!$C$4:$N$4,0))*$E42 -> 22.464563 | H42: =INDEX('Monthly Engine'!$C$28:$N$28,MATCH($D42,'Monthly Engine'!$C$4:$N$4,0))*$E42 -> 167.06399 | I42: =(INDEX('Monthly Engine'!$C$31:$N$31,MATCH($D42,'Monthly Engine'!$C$4:$N$4,0))+INDEX('Monthly Engine'!$C$33:$N$33,MATCH($D42,'Monthly Engine'!$C$4:$N$4,0)))*$E42 -> 309.86458 | J42: =H42+I42 -> 476.92857 | K42: =INDEX('Monthly Engine'!$C$29:$N$29,MATCH($D42,'Monthly Engine'!$C$4:$N$4,0)) -> 904.8233 | L42: =INDEX('Monthly Engine'!$C$35:$N$35,MATCH($D42,'Monthly Engine'!$C$4:$N$4,0))*$E42 -> 309321.56 | M42: =INDEX('Monthly Engine'!$C$39:$N$39,MATCH($D42,'Monthly Engine'!$C$4:$N$4,0))*$E42 -> 2651.5909 | N42: =INDEX('Monthly Engine'!$C$40:$N$40,MATCH($D42,'Monthly Engine'!$C$4:$N$4,0))/4 -> 24000 | O42: =N42-M42 -> 21348.409 | P42: =INDEX('Monthly Engine'!$C$50:$N$50,MATCH($D42,'Monthly Engine'!$C$4:$N$4,0))*$E42 -> 151968.56 | Q42: =INDEX('Monthly Engine'!$C$60:$N$60,MATCH($D42,'Monthly Engine'!$C$4:$N$4,0))*$E42 -> 40941.721
A43: F39 | B43: 46470 | C43: 46476 | D43: Mar-27 | E43: 0.25 | F43: =INDEX('Monthly Engine'!$C$13:$N$13,MATCH($D43,'Monthly Engine'!$C$4:$N$4,0))*$E43 -> 61.343029 | G43: =INDEX('Monthly Engine'!$C$14:$N$14,MATCH($D43,'Monthly Engine'!$C$4:$N$4,0))*$E43 -> 22.464563 | H43: =INDEX('Monthly Engine'!$C$28:$N$28,MATCH($D43,'Monthly Engine'!$C$4:$N$4,0))*$E43 -> 167.06399 | I43: =(INDEX('Monthly Engine'!$C$31:$N$31,MATCH($D43,'Monthly Engine'!$C$4:$N$4,0))+INDEX('Monthly Engine'!$C$33:$N$33,MATCH($D43,'Monthly Engine'!$C$4:$N$4,0)))*$E43 -> 309.86458 | J43: =H43+I43 -> 476.92857 | K43: =INDEX('Monthly Engine'!$C$29:$N$29,MATCH($D43,'Monthly Engine'!$C$4:$N$4,0)) -> 904.8233 | L43: =INDEX('Monthly Engine'!$C$35:$N$35,MATCH($D43,'Monthly Engine'!$C$4:$N$4,0))*$E43 -> 309321.56 | M43: =INDEX('Monthly Engine'!$C$39:$N$39,MATCH($D43,'Monthly Engine'!$C$4:$N$4,0))*$E43 -> 2651.5909 | N43: =INDEX('Monthly Engine'!$C$40:$N$40,MATCH($D43,'Monthly Engine'!$C$4:$N$4,0))/4 -> 24000 | O43: =N43-M43 -> 21348.409 | P43: =INDEX('Monthly Engine'!$C$50:$N$50,MATCH($D43,'Monthly Engine'!$C$4:$N$4,0))*$E43 -> 151968.56 | Q43: =INDEX('Monthly Engine'!$C$60:$N$60,MATCH($D43,'Monthly Engine'!$C$4:$N$4,0))*$E43 -> 40941.721
A44: F40 | B44: 46477 | C44: 46483 | D44: Apr-27 | E44: 0.25 | F44: =INDEX('Monthly Engine'!$C$13:$N$13,MATCH($D44,'Monthly Engine'!$C$4:$N$4,0))*$E44 -> 76.12689 | G44: =INDEX('Monthly Engine'!$C$14:$N$14,MATCH($D44,'Monthly Engine'!$C$4:$N$4,0))*$E44 -> 25.774718 | H44: =INDEX('Monthly Engine'!$C$28:$N$28,MATCH($D44,'Monthly Engine'!$C$4:$N$4,0))*$E44 -> 200.66581 | I44: =(INDEX('Monthly Engine'!$C$31:$N$31,MATCH($D44,'Monthly Engine'!$C$4:$N$4,0))+INDEX('Monthly Engine'!$C$33:$N$33,MATCH($D44,'Monthly Engine'!$C$4:$N$4,0)))*$E44 -> 416.8125 | J44: =H44+I44 -> 617.47831 | K44: =INDEX('Monthly Engine'!$C$29:$N$29,MATCH($D44,'Monthly Engine'!$C$4:$N$4,0)) -> 914.77636 | L44: =INDEX('Monthly Engine'!$C$35:$N$35,MATCH($D44,'Monthly Engine'!$C$4:$N$4,0))*$E44 -> 396050.96 | M44: =INDEX('Monthly Engine'!$C$39:$N$39,MATCH($D44,'Monthly Engine'!$C$4:$N$4,0))*$E44 -> 3415.4503 | N44: =INDEX('Monthly Engine'!$C$40:$N$40,MATCH($D44,'Monthly Engine'!$C$4:$N$4,0))/4 -> 24000 | O44: =N44-M44 -> 20584.55 | P44: =INDEX('Monthly Engine'!$C$50:$N$50,MATCH($D44,'Monthly Engine'!$C$4:$N$4,0))*$E44 -> 195564.67 | Q44: =INDEX('Monthly Engine'!$C$60:$N$60,MATCH($D44,'Monthly Engine'!$C$4:$N$4,0))*$E44 -> 82376.487
A45: F41 | B45: 46484 | C45: 46490 | D45: Apr-27 | E45: 0.25 | F45: =INDEX('Monthly Engine'!$C$13:$N$13,MATCH($D45,'Monthly Engine'!$C$4:$N$4,0))*$E45 -> 76.12689 | G45: =INDEX('Monthly Engine'!$C$14:$N$14,MATCH($D45,'Monthly Engine'!$C$4:$N$4,0))*$E45 -> 25.774718 | H45: =INDEX('Monthly Engine'!$C$28:$N$28,MATCH($D45,'Monthly Engine'!$C$4:$N$4,0))*$E45 -> 200.66581 | I45: =(INDEX('Monthly Engine'!$C$31:$N$31,MATCH($D45,'Monthly Engine'!$C$4:$N$4,0))+INDEX('Monthly Engine'!$C$33:$N$33,MATCH($D45,'Monthly Engine'!$C$4:$N$4,0)))*$E45 -> 416.8125 | J45: =H45+I45 -> 617.47831 | K45: =INDEX('Monthly Engine'!$C$29:$N$29,MATCH($D45,'Monthly Engine'!$C$4:$N$4,0)) -> 914.77636 | L45: =INDEX('Monthly Engine'!$C$35:$N$35,MATCH($D45,'Monthly Engine'!$C$4:$N$4,0))*$E45 -> 396050.96 | M45: =INDEX('Monthly Engine'!$C$39:$N$39,MATCH($D45,'Monthly Engine'!$C$4:$N$4,0))*$E45 -> 3415.4503 | N45: =INDEX('Monthly Engine'!$C$40:$N$40,MATCH($D45,'Monthly Engine'!$C$4:$N$4,0))/4 -> 24000 | O45: =N45-M45 -> 20584.55 | P45: =INDEX('Monthly Engine'!$C$50:$N$50,MATCH($D45,'Monthly Engine'!$C$4:$N$4,0))*$E45 -> 195564.67 | Q45: =INDEX('Monthly Engine'!$C$60:$N$60,MATCH($D45,'Monthly Engine'!$C$4:$N$4,0))*$E45 -> 82376.487
A46: F42 | B46: 46491 | C46: 46497 | D46: Apr-27 | E46: 0.25 | F46: =INDEX('Monthly Engine'!$C$13:$N$13,MATCH($D46,'Monthly Engine'!$C$4:$N$4,0))*$E46 -> 76.12689 | G46: =INDEX('Monthly Engine'!$C$14:$N$14,MATCH($D46,'Monthly Engine'!$C$4:$N$4,0))*$E46 -> 25.774718 | H46: =INDEX('Monthly Engine'!$C$28:$N$28,MATCH($D46,'Monthly Engine'!$C$4:$N$4,0))*$E46 -> 200.66581 | I46: =(INDEX('Monthly Engine'!$C$31:$N$31,MATCH($D46,'Monthly Engine'!$C$4:$N$4,0))+INDEX('Monthly Engine'!$C$33:$N$33,MATCH($D46,'Monthly Engine'!$C$4:$N$4,0)))*$E46 -> 416.8125 | J46: =H46+I46 -> 617.47831 | K46: =INDEX('Monthly Engine'!$C$29:$N$29,MATCH($D46,'Monthly Engine'!$C$4:$N$4,0)) -> 914.77636 | L46: =INDEX('Monthly Engine'!$C$35:$N$35,MATCH($D46,'Monthly Engine'!$C$4:$N$4,0))*$E46 -> 396050.96 | M46: =INDEX('Monthly Engine'!$C$39:$N$39,MATCH($D46,'Monthly Engine'!$C$4:$N$4,0))*$E46 -> 3415.4503 | N46: =INDEX('Monthly Engine'!$C$40:$N$40,MATCH($D46,'Monthly Engine'!$C$4:$N$4,0))/4 -> 24000 | O46: =N46-M46 -> 20584.55 | P46: =INDEX('Monthly Engine'!$C$50:$N$50,MATCH($D46,'Monthly Engine'!$C$4:$N$4,0))*$E46 -> 195564.67 | Q46: =INDEX('Monthly Engine'!$C$60:$N$60,MATCH($D46,'Monthly Engine'!$C$4:$N$4,0))*$E46 -> 82376.487
A47: F43 | B47: 46498 | C47: 46504 | D47: Apr-27 | E47: 0.25 | F47: =INDEX('Monthly Engine'!$C$13:$N$13,MATCH($D47,'Monthly Engine'!$C$4:$N$4,0))*$E47 -> 76.12689 | G47: =INDEX('Monthly Engine'!$C$14:$N$14,MATCH($D47,'Monthly Engine'!$C$4:$N$4,0))*$E47 -> 25.774718 | H47: =INDEX('Monthly Engine'!$C$28:$N$28,MATCH($D47,'Monthly Engine'!$C$4:$N$4,0))*$E47 -> 200.66581 | I47: =(INDEX('Monthly Engine'!$C$31:$N$31,MATCH($D47,'Monthly Engine'!$C$4:$N$4,0))+INDEX('Monthly Engine'!$C$33:$N$33,MATCH($D47,'Monthly Engine'!$C$4:$N$4,0)))*$E47 -> 416.8125 | J47: =H47+I47 -> 617.47831 | K47: =INDEX('Monthly Engine'!$C$29:$N$29,MATCH($D47,'Monthly Engine'!$C$4:$N$4,0)) -> 914.77636 | L47: =INDEX('Monthly Engine'!$C$35:$N$35,MATCH($D47,'Monthly Engine'!$C$4:$N$4,0))*$E47 -> 396050.96 | M47: =INDEX('Monthly Engine'!$C$39:$N$39,MATCH($D47,'Monthly Engine'!$C$4:$N$4,0))*$E47 -> 3415.4503 | N47: =INDEX('Monthly Engine'!$C$40:$N$40,MATCH($D47,'Monthly Engine'!$C$4:$N$4,0))/4 -> 24000 | O47: =N47-M47 -> 20584.55 | P47: =INDEX('Monthly Engine'!$C$50:$N$50,MATCH($D47,'Monthly Engine'!$C$4:$N$4,0))*$E47 -> 195564.67 | Q47: =INDEX('Monthly Engine'!$C$60:$N$60,MATCH($D47,'Monthly Engine'!$C$4:$N$4,0))*$E47 -> 82376.487
A48: F44 | B48: 46505 | C48: 46511 | D48: May-27 | E48: 0.2 | F48: =INDEX('Monthly Engine'!$C$13:$N$13,MATCH($D48,'Monthly Engine'!$C$4:$N$4,0))*$E48 -> 74.19952 | G48: =INDEX('Monthly Engine'!$C$14:$N$14,MATCH($D48,'Monthly Engine'!$C$4:$N$4,0))*$E48 -> 23.173203 | H48: =INDEX('Monthly Engine'!$C$28:$N$28,MATCH($D48,'Monthly Engine'!$C$4:$N$4,0))*$E48 -> 194.62194 | I48: =(INDEX('Monthly Engine'!$C$31:$N$31,MATCH($D48,'Monthly Engine'!$C$4:$N$4,0))+INDEX('Monthly Engine'!$C$33:$N$33,MATCH($D48,'Monthly Engine'!$C$4:$N$4,0)))*$E48 -> 393.14167 | J48: =H48+I48 -> 587.7636 | K48: =INDEX('Monthly Engine'!$C$29:$N$29,MATCH($D48,'Monthly Engine'!$C$4:$N$4,0)) -> 924.8389 | L48: =INDEX('Monthly Engine'!$C$35:$N$35,MATCH($D48,'Monthly Engine'!$C$4:$N$4,0))*$E48 -> 380220.37 | M48: =INDEX('Monthly Engine'!$C$39:$N$39,MATCH($D48,'Monthly Engine'!$C$4:$N$4,0))*$E48 -> 3283.1858 | N48: =INDEX('Monthly Engine'!$C$40:$N$40,MATCH($D48,'Monthly Engine'!$C$4:$N$4,0))/5 -> 28800 | O48: =N48-M48 -> 25516.814 | P48: =INDEX('Monthly Engine'!$C$50:$N$50,MATCH($D48,'Monthly Engine'!$C$4:$N$4,0))*$E48 -> 189577.35 | Q48: =INDEX('Monthly Engine'!$C$60:$N$60,MATCH($D48,'Monthly Engine'!$C$4:$N$4,0))*$E48 -> 92787.912
A49: F45 | B49: 46512 | C49: 46518 | D49: May-27 | E49: 0.2 | F49: =INDEX('Monthly Engine'!$C$13:$N$13,MATCH($D49,'Monthly Engine'!$C$4:$N$4,0))*$E49 -> 74.19952 | G49: =INDEX('Monthly Engine'!$C$14:$N$14,MATCH($D49,'Monthly Engine'!$C$4:$N$4,0))*$E49 -> 23.173203 | H49: =INDEX('Monthly Engine'!$C$28:$N$28,MATCH($D49,'Monthly Engine'!$C$4:$N$4,0))*$E49 -> 194.62194 | I49: =(INDEX('Monthly Engine'!$C$31:$N$31,MATCH($D49,'Monthly Engine'!$C$4:$N$4,0))+INDEX('Monthly Engine'!$C$33:$N$33,MATCH($D49,'Monthly Engine'!$C$4:$N$4,0)))*$E49 -> 393.14167 | J49: =H49+I49 -> 587.7636 | K49: =INDEX('Monthly Engine'!$C$29:$N$29,MATCH($D49,'Monthly Engine'!$C$4:$N$4,0)) -> 924.8389 | L49: =INDEX('Monthly Engine'!$C$35:$N$35,MATCH($D49,'Monthly Engine'!$C$4:$N$4,0))*$E49 -> 380220.37 | M49: =INDEX('Monthly Engine'!$C$39:$N$39,MATCH($D49,'Monthly Engine'!$C$4:$N$4,0))*$E49 -> 3283.1858 | N49: =INDEX('Monthly Engine'!$C$40:$N$40,MATCH($D49,'Monthly Engine'!$C$4:$N$4,0))/5 -> 28800 | O49: =N49-M49 -> 25516.814 | P49: =INDEX('Monthly Engine'!$C$50:$N$50,MATCH($D49,'Monthly Engine'!$C$4:$N$4,0))*$E49 -> 189577.35 | Q49: =INDEX('Monthly Engine'!$C$60:$N$60,MATCH($D49,'Monthly Engine'!$C$4:$N$4,0))*$E49 -> 92787.912
A50: F46 | B50: 46519 | C50: 46525 | D50: May-27 | E50: 0.2 | F50: =INDEX('Monthly Engine'!$C$13:$N$13,MATCH($D50,'Monthly Engine'!$C$4:$N$4,0))*$E50 -> 74.19952 | G50: =INDEX('Monthly Engine'!$C$14:$N$14,MATCH($D50,'Monthly Engine'!$C$4:$N$4,0))*$E50 -> 23.173203 | H50: =INDEX('Monthly Engine'!$C$28:$N$28,MATCH($D50,'Monthly Engine'!$C$4:$N$4,0))*$E50 -> 194.62194 | I50: =(INDEX('Monthly Engine'!$C$31:$N$31,MATCH($D50,'Monthly Engine'!$C$4:$N$4,0))+INDEX('Monthly Engine'!$C$33:$N$33,MATCH($D50,'Monthly Engine'!$C$4:$N$4,0)))*$E50 -> 393.14167 | J50: =H50+I50 -> 587.7636 | K50: =INDEX('Monthly Engine'!$C$29:$N$29,MATCH($D50,'Monthly Engine'!$C$4:$N$4,0)) -> 924.8389 | L50: =INDEX('Monthly Engine'!$C$35:$N$35,MATCH($D50,'Monthly Engine'!$C$4:$N$4,0))*$E50 -> 380220.37 | M50: =INDEX('Monthly Engine'!$C$39:$N$39,MATCH($D50,'Monthly Engine'!$C$4:$N$4,0))*$E50 -> 3283.1858 | N50: =INDEX('Monthly Engine'!$C$40:$N$40,MATCH($D50,'Monthly Engine'!$C$4:$N$4,0))/5 -> 28800 | O50: =N50-M50 -> 25516.814 | P50: =INDEX('Monthly Engine'!$C$50:$N$50,MATCH($D50,'Monthly Engine'!$C$4:$N$4,0))*$E50 -> 189577.35 | Q50: =INDEX('Monthly Engine'!$C$60:$N$60,MATCH($D50,'Monthly Engine'!$C$4:$N$4,0))*$E50 -> 92787.912
A51: F47 | B51: 46526 | C51: 46532 | D51: May-27 | E51: 0.2 | F51: =INDEX('Monthly Engine'!$C$13:$N$13,MATCH($D51,'Monthly Engine'!$C$4:$N$4,0))*$E51 -> 74.19952 | G51: =INDEX('Monthly Engine'!$C$14:$N$14,MATCH($D51,'Monthly Engine'!$C$4:$N$4,0))*$E51 -> 23.173203 | H51: =INDEX('Monthly Engine'!$C$28:$N$28,MATCH($D51,'Monthly Engine'!$C$4:$N$4,0))*$E51 -> 194.62194 | I51: =(INDEX('Monthly Engine'!$C$31:$N$31,MATCH($D51,'Monthly Engine'!$C$4:$N$4,0))+INDEX('Monthly Engine'!$C$33:$N$33,MATCH($D51,'Monthly Engine'!$C$4:$N$4,0)))*$E51 -> 393.14167 | J51: =H51+I51 -> 587.7636 | K51: =INDEX('Monthly Engine'!$C$29:$N$29,MATCH($D51,'Monthly Engine'!$C$4:$N$4,0)) -> 924.8389 | L51: =INDEX('Monthly Engine'!$C$35:$N$35,MATCH($D51,'Monthly Engine'!$C$4:$N$4,0))*$E51 -> 380220.37 | M51: =INDEX('Monthly Engine'!$C$39:$N$39,MATCH($D51,'Monthly Engine'!$C$4:$N$4,0))*$E51 -> 3283.1858 | N51: =INDEX('Monthly Engine'!$C$40:$N$40,MATCH($D51,'Monthly Engine'!$C$4:$N$4,0))/5 -> 28800 | O51: =N51-M51 -> 25516.814 | P51: =INDEX('Monthly Engine'!$C$50:$N$50,MATCH($D51,'Monthly Engine'!$C$4:$N$4,0))*$E51 -> 189577.35 | Q51: =INDEX('Monthly Engine'!$C$60:$N$60,MATCH($D51,'Monthly Engine'!$C$4:$N$4,0))*$E51 -> 92787.912
A52: F48 | B52: 46533 | C52: 46539 | D52: May-27 | E52: 0.2 | F52: =INDEX('Monthly Engine'!$C$13:$N$13,MATCH($D52,'Monthly Engine'!$C$4:$N$4,0))*$E52 -> 74.19952 | G52: =INDEX('Monthly Engine'!$C$14:$N$14,MATCH($D52,'Monthly Engine'!$C$4:$N$4,0))*$E52 -> 23.173203 | H52: =INDEX('Monthly Engine'!$C$28:$N$28,MATCH($D52,'Monthly Engine'!$C$4:$N$4,0))*$E52 -> 194.62194 | I52: =(INDEX('Monthly Engine'!$C$31:$N$31,MATCH($D52,'Monthly Engine'!$C$4:$N$4,0))+INDEX('Monthly Engine'!$C$33:$N$33,MATCH($D52,'Monthly Engine'!$C$4:$N$4,0)))*$E52 -> 393.14167 | J52: =H52+I52 -> 587.7636 | K52: =INDEX('Monthly Engine'!$C$29:$N$29,MATCH($D52,'Monthly Engine'!$C$4:$N$4,0)) -> 924.8389 | L52: =INDEX('Monthly Engine'!$C$35:$N$35,MATCH($D52,'Monthly Engine'!$C$4:$N$4,0))*$E52 -> 380220.37 | M52: =INDEX('Monthly Engine'!$C$39:$N$39,MATCH($D52,'Monthly Engine'!$C$4:$N$4,0))*$E52 -> 3283.1858 | N52: =INDEX('Monthly Engine'!$C$40:$N$40,MATCH($D52,'Monthly Engine'!$C$4:$N$4,0))/5 -> 28800 | O52: =N52-M52 -> 25516.814 | P52: =INDEX('Monthly Engine'!$C$50:$N$50,MATCH($D52,'Monthly Engine'!$C$4:$N$4,0))*$E52 -> 189577.35 | Q52: =INDEX('Monthly Engine'!$C$60:$N$60,MATCH($D52,'Monthly Engine'!$C$4:$N$4,0))*$E52 -> 92787.912
A53: F49 | B53: 46540 | C53: 46546 | D53: Jun-27 | E53: 0.25 | F53: =INDEX('Monthly Engine'!$C$13:$N$13,MATCH($D53,'Monthly Engine'!$C$4:$N$4,0))*$E53 -> 104.02011 | G53: =INDEX('Monthly Engine'!$C$14:$N$14,MATCH($D53,'Monthly Engine'!$C$4:$N$4,0))*$E53 -> 32.192258 | H53: =INDEX('Monthly Engine'!$C$28:$N$28,MATCH($D53,'Monthly Engine'!$C$4:$N$4,0))*$E53 -> 285.24508 | I53: =(INDEX('Monthly Engine'!$C$31:$N$31,MATCH($D53,'Monthly Engine'!$C$4:$N$4,0))+INDEX('Monthly Engine'!$C$33:$N$33,MATCH($D53,'Monthly Engine'!$C$4:$N$4,0)))*$E53 -> 527.5 | J53: =H53+I53 -> 812.74508 | K53: =INDEX('Monthly Engine'!$C$29:$N$29,MATCH($D53,'Monthly Engine'!$C$4:$N$4,0)) -> 935.01212 | L53: =INDEX('Monthly Engine'!$C$35:$N$35,MATCH($D53,'Monthly Engine'!$C$4:$N$4,0))*$E53 -> 535152.61 | M53: =INDEX('Monthly Engine'!$C$39:$N$39,MATCH($D53,'Monthly Engine'!$C$4:$N$4,0))*$E53 -> 4619.1126 | N53: =INDEX('Monthly Engine'!$C$40:$N$40,MATCH($D53,'Monthly Engine'!$C$4:$N$4,0))/4 -> 36000 | O53: =N53-M53 -> 31380.887 | P53: =INDEX('Monthly Engine'!$C$50:$N$50,MATCH($D53,'Monthly Engine'!$C$4:$N$4,0))*$E53 -> 269866.46 | Q53: =INDEX('Monthly Engine'!$C$60:$N$60,MATCH($D53,'Monthly Engine'!$C$4:$N$4,0))*$E53 -> 140564.28
A54: F50 | B54: 46547 | C54: 46553 | D54: Jun-27 | E54: 0.25 | F54: =INDEX('Monthly Engine'!$C$13:$N$13,MATCH($D54,'Monthly Engine'!$C$4:$N$4,0))*$E54 -> 104.02011 | G54: =INDEX('Monthly Engine'!$C$14:$N$14,MATCH($D54,'Monthly Engine'!$C$4:$N$4,0))*$E54 -> 32.192258 | H54: =INDEX('Monthly Engine'!$C$28:$N$28,MATCH($D54,'Monthly Engine'!$C$4:$N$4,0))*$E54 -> 285.24508 | I54: =(INDEX('Monthly Engine'!$C$31:$N$31,MATCH($D54,'Monthly Engine'!$C$4:$N$4,0))+INDEX('Monthly Engine'!$C$33:$N$33,MATCH($D54,'Monthly Engine'!$C$4:$N$4,0)))*$E54 -> 527.5 | J54: =H54+I54 -> 812.74508 | K54: =INDEX('Monthly Engine'!$C$29:$N$29,MATCH($D54,'Monthly Engine'!$C$4:$N$4,0)) -> 935.01212 | L54: =INDEX('Monthly Engine'!$C$35:$N$35,MATCH($D54,'Monthly Engine'!$C$4:$N$4,0))*$E54 -> 535152.61 | M54: =INDEX('Monthly Engine'!$C$39:$N$39,MATCH($D54,'Monthly Engine'!$C$4:$N$4,0))*$E54 -> 4619.1126 | N54: =INDEX('Monthly Engine'!$C$40:$N$40,MATCH($D54,'Monthly Engine'!$C$4:$N$4,0))/4 -> 36000 | O54: =N54-M54 -> 31380.887 | P54: =INDEX('Monthly Engine'!$C$50:$N$50,MATCH($D54,'Monthly Engine'!$C$4:$N$4,0))*$E54 -> 269866.46 | Q54: =INDEX('Monthly Engine'!$C$60:$N$60,MATCH($D54,'Monthly Engine'!$C$4:$N$4,0))*$E54 -> 140564.28
A55: F51 | B55: 46554 | C55: 46560 | D55: Jun-27 | E55: 0.25 | F55: =INDEX('Monthly Engine'!$C$13:$N$13,MATCH($D55,'Monthly Engine'!$C$4:$N$4,0))*$E55 -> 104.02011 | G55: =INDEX('Monthly Engine'!$C$14:$N$14,MATCH($D55,'Monthly Engine'!$C$4:$N$4,0))*$E55 -> 32.192258 | H55: =INDEX('Monthly Engine'!$C$28:$N$28,MATCH($D55,'Monthly Engine'!$C$4:$N$4,0))*$E55 -> 285.24508 | I55: =(INDEX('Monthly Engine'!$C$31:$N$31,MATCH($D55,'Monthly Engine'!$C$4:$N$4,0))+INDEX('Monthly Engine'!$C$33:$N$33,MATCH($D55,'Monthly Engine'!$C$4:$N$4,0)))*$E55 -> 527.5 | J55: =H55+I55 -> 812.74508 | K55: =INDEX('Monthly Engine'!$C$29:$N$29,MATCH($D55,'Monthly Engine'!$C$4:$N$4,0)) -> 935.01212 | L55: =INDEX('Monthly Engine'!$C$35:$N$35,MATCH($D55,'Monthly Engine'!$C$4:$N$4,0))*$E55 -> 535152.61 | M55: =INDEX('Monthly Engine'!$C$39:$N$39,MATCH($D55,'Monthly Engine'!$C$4:$N$4,0))*$E55 -> 4619.1126 | N55: =INDEX('Monthly Engine'!$C$40:$N$40,MATCH($D55,'Monthly Engine'!$C$4:$N$4,0))/4 -> 36000 | O55: =N55-M55 -> 31380.887 | P55: =INDEX('Monthly Engine'!$C$50:$N$50,MATCH($D55,'Monthly Engine'!$C$4:$N$4,0))*$E55 -> 269866.46 | Q55: =INDEX('Monthly Engine'!$C$60:$N$60,MATCH($D55,'Monthly Engine'!$C$4:$N$4,0))*$E55 -> 140564.28
A56: F52 | B56: 46561 | C56: 46567 | D56: Jun-27 | E56: 0.25 | F56: =INDEX('Monthly Engine'!$C$13:$N$13,MATCH($D56,'Monthly Engine'!$C$4:$N$4,0))*$E56 -> 104.02011 | G56: =INDEX('Monthly Engine'!$C$14:$N$14,MATCH($D56,'Monthly Engine'!$C$4:$N$4,0))*$E56 -> 32.192258 | H56: =INDEX('Monthly Engine'!$C$28:$N$28,MATCH($D56,'Monthly Engine'!$C$4:$N$4,0))*$E56 -> 285.24508 | I56: =(INDEX('Monthly Engine'!$C$31:$N$31,MATCH($D56,'Monthly Engine'!$C$4:$N$4,0))+INDEX('Monthly Engine'!$C$33:$N$33,MATCH($D56,'Monthly Engine'!$C$4:$N$4,0)))*$E56 -> 527.5 | J56: =H56+I56 -> 812.74508 | K56: =INDEX('Monthly Engine'!$C$29:$N$29,MATCH($D56,'Monthly Engine'!$C$4:$N$4,0)) -> 935.01212 | L56: =INDEX('Monthly Engine'!$C$35:$N$35,MATCH($D56,'Monthly Engine'!$C$4:$N$4,0))*$E56 -> 535152.61 | M56: =INDEX('Monthly Engine'!$C$39:$N$39,MATCH($D56,'Monthly Engine'!$C$4:$N$4,0))*$E56 -> 4619.1126 | N56: =INDEX('Monthly Engine'!$C$40:$N$40,MATCH($D56,'Monthly Engine'!$C$4:$N$4,0))/4 -> 36000 | O56: =N56-M56 -> 31380.887 | P56: =INDEX('Monthly Engine'!$C$50:$N$50,MATCH($D56,'Monthly Engine'!$C$4:$N$4,0))*$E56 -> 269866.46 | Q56: =INDEX('Monthly Engine'!$C$60:$N$60,MATCH($D56,'Monthly Engine'!$C$4:$N$4,0))*$E56 -> 140564.28
D57: TOTAL / TIE-OUT | J57: =SUM(J5:J56) -> 17865.754 | L57: =SUM(L5:L56) -> 11848559 | P57: =SUM(P5:P56) -> 5845587.5 | Q57: =SUM(Q5:Q56) -> 1236257.7

Sheet Monthly Rollup & Cash
B1: MONTHLY ROLLUP — PATH TO ₹1 CRORE MRR (live: reflects the Assumptions & Log scenario switch)
B3: Month | C3: Jul-26 | D3: Aug-26 | E3: Sep-26 | F3: Oct-26 | G3: Nov-26 | H3: Dec-26 | I3: Jan-27 | J3: Feb-27 | K3: Mar-27 | L3: Apr-27 | M3: May-27 | N3: Jun-27
B4: Net revenue (MRR), ₹ | C4: ='Monthly Engine'!C35 -> 215641.05 | D4: ='Monthly Engine'!D35 -> 300654.36 | E4: ='Monthly Engine'!E35 -> 442991.86 | F4: ='Monthly Engine'!F35 -> 609814.02 | G4: ='Monthly Engine'!G35 -> 729803.94 | H4: ='Monthly Engine'!H35 -> 768754.26 | I4: ='Monthly Engine'!I35 -> 904329.83 | J4: ='Monthly Engine'!J35 -> 1013440.1 | ... N4: ='Monthly Engine'!N35 -> 2140610.4
B5: MoM growth % | C5: =(C4-251242)/251242 -> -0.14169984 | D5: =(D4-C4)/C4 -> 0.39423527 | E5: =(E4-D4)/D4 -> 0.47342571 | F5: =(F4-E4)/E4 -> 0.37658065 | G5: =(G4-F4)/F4 -> 0.19676477 | H5: =(H4-G4)/G4 -> 0.053370937 | I5: =(I4-H4)/H4 -> 0.17635749 | J5: =(J4-I4)/I4 -> 0.12065314 | K5: =(K4-J4)/J4 -> 0.22087755 | ... N5: =(N4-M4)/M4 -> 0.12598409
B6: Multiple vs Jun-26 actual (₹2,51,242) | C6: =C4/251242 -> 0.85830016 | D6: =D4/251242 -> 1.1966724 | E6: =E4/251242 -> 1.7632078 | F6: =F4/251242 -> 2.4271978 | G6: =G4/251242 -> 2.9047848 | H6: =H4/251242 -> 3.0598159 | I6: =I4/251242 -> 3.5994373 | J6: =J4/251242 -> 4.0337207 | ... N6: =N4/251242 -> 8.5201138
B7: % of ₹1cr target | C7: =C4/10000000 -> 0.021564105 | D7: =D4/10000000 -> 0.030065436 | E7: =E4/10000000 -> 0.044299186 | F7: =F4/10000000 -> 0.060981402 | G7: =G4/10000000 -> 0.072980394 | H7: =H4/10000000 -> 0.076875426 | I7: =I4/10000000 -> 0.090432983 | J7: =J4/10000000 -> 0.10134401 | ... N7: =N4/10000000 -> 0.21406104
B9: D2C orders | C9: ='Monthly Engine'!C28 -> 260.12189 | D9: ='Monthly Engine'!D28 -> 302.46205 | E9: ='Monthly Engine'!E28 -> 372.25611 | F9: ='Monthly Engine'!F28 -> 439.25268 | G9: ='Monthly Engine'!G28 -> 482.81779 | H9: ='Monthly Engine'!H28 -> 492.97032 | I9: ='Monthly Engine'!I28 -> 539.76249 | J9: ='Monthly Engine'!J28 -> 580.50142 | ... N9: ='Monthly Engine'!N28 -> 1140.9803
B10: — of which: Subscription orders | C10: ='Monthly Engine'!C25 -> 55.973367 | D10: ='Monthly Engine'!D25 -> 65.769613 | E10: ='Monthly Engine'!E25 -> 78.715266 | F10: ='Monthly Engine'!F25 -> 97.581968 | G10: ='Monthly Engine'!G25 -> 117.55381 | H10: ='Monthly Engine'!H25 -> 134.11061 | I10: ='Monthly Engine'!I25 -> 154.98006 | J10: ='Monthly Engine'!J25 -> 177.88634 | ... N10: ='Monthly Engine'!N25 -> 381.45802
B11: Marketplace + QC orders | C11: ='Monthly Engine'!C31+'Monthly Engine'!C33 -> 0 | D11: ='Monthly Engine'!D31+'Monthly Engine'!D33 -> 81.583333 | E11: ='Monthly Engine'!E31+'Monthly Engine'!E33 -> 240.25 | F11: ='Monthly Engine'!F31+'Monthly Engine'!F33 -> 448.375 | G11: ='Monthly Engine'!G31+'Monthly Engine'!G33 -> 603.5 | H11: ='Monthly Engine'!H31+'Monthly Engine'!H33 -> 655.95833 | I11: ='Monthly Engine'!I31+'Monthly Engine'!I33 -> 832.5 | J11: ='Monthly Engine'!J31+'Monthly Engine'!J33 -> 966.125 | ... N11: ='Monthly Engine'!N31+'Monthly Engine'!N33 -> 2110
B13: Cans required | C13: ='Monthly Engine'!C39 -> 1612.7557 | D13: ='Monthly Engine'!D39 -> 2362.4682 | E13: ='Monthly Engine'!E39 -> 3584.619 | F13: ='Monthly Engine'!F39 -> 5040.6438 | G13: ='Monthly Engine'!G39 -> 6099.5185 | H13: ='Monthly Engine'!H39 -> 6458.8952 | I13: ='Monthly Engine'!I39 -> 7662.4597 | J13: ='Monthly Engine'!J39 -> 8633.4703 | ... N13: ='Monthly Engine'!N39 -> 18476.45
B14: Capacity ceiling | C14: ='Monthly Engine'!C40 -> 48000 | D14: ='Monthly Engine'!D40 -> 48000 | E14: ='Monthly Engine'!E40 -> 48000 | F14: ='Monthly Engine'!F40 -> 96000 | G14: ='Monthly Engine'!G40 -> 96000 | H14: ='Monthly Engine'!H40 -> 96000 | I14: ='Monthly Engine'!I40 -> 96000 | J14: ='Monthly Engine'!J40 -> 96000 | ... N14: ='Monthly Engine'!N40 -> 144000
B15: Capacity headroom | C15: ='Monthly Engine'!C41 -> 46387.244 | D15: ='Monthly Engine'!D41 -> 45637.532 | E15: ='Monthly Engine'!E41 -> 44415.381 | F15: ='Monthly Engine'!F41 -> 90959.356 | G15: ='Monthly Engine'!G41 -> 89900.482 | H15: ='Monthly Engine'!H41 -> 89541.105 | I15: ='Monthly Engine'!I41 -> 88337.54 | J15: ='Monthly Engine'!J41 -> 87366.53 | ... N15: ='Monthly Engine'!N41 -> 125523.55
B16: Capacity utilisation % | C16: =C13/C14 -> 0.033599078 | D16: =D13/D14 -> 0.049218088 | E16: =E13/E14 -> 0.074679562 | F16: =F13/F14 -> 0.052506706 | G16: =G13/G14 -> 0.063536651 | H16: =H13/H14 -> 0.067280158 | I16: =I13/I14 -> 0.079817289 | J16: =J13/J14 -> 0.089931982 | ... N16: =N13/N14 -> 0.12830868
B18: CM1, ₹ | C18: ='Monthly Engine'!C50 -> 109880.69 | D18: ='Monthly Engine'!D50 -> 148951.51 | E18: ='Monthly Engine'!E50 -> 215672.5 | F18: ='Monthly Engine'!F50 -> 293981.47 | G18: ='Monthly Engine'!G50 -> 351809.02 | H18: ='Monthly Engine'!H50 -> 372719.56 | I18: ='Monthly Engine'!I50 -> 439632.25 | J18: ='Monthly Engine'!J50 -> 495490.1 | ... N18: ='Monthly Engine'!N50 -> 1079465.8
B19: CM1 % | C19: ='Monthly Engine'!C51 -> 0.50955368 | D19: ='Monthly Engine'!D51 -> 0.49542443 | E19: ='Monthly Engine'!E51 -> 0.48685431 | F19: ='Monthly Engine'!F51 -> 0.48208381 | G19: ='Monthly Engine'!G51 -> 0.48205964 | H19: ='Monthly Engine'!H51 -> 0.48483577 | I19: ='Monthly Engine'!I51 -> 0.48614149 | J19: ='Monthly Engine'!J51 -> 0.488919 | ... N19: ='Monthly Engine'!N51 -> 0.50427945
B20: CM2, ₹ | C20: ='Monthly Engine'!C57 -> -17619.31 | D20: ='Monthly Engine'!D57 -> 15551.513 | E20: ='Monthly Engine'!E57 -> 76084.995 | F20: ='Monthly Engine'!F57 -> 147904.59 | G20: ='Monthly Engine'!G57 -> 198925.81 | H20: ='Monthly Engine'!H57 -> 212697.18 | I20: ='Monthly Engine'!I57 -> 272121.25 | J20: ='Monthly Engine'!J57 -> 320123.55 | ... N20: ='Monthly Engine'!N57 -> 822757.11
B21: EBITDA, ₹ | C21: ='Monthly Engine'!C60 -> -163119.31 | D21: ='Monthly Engine'!D60 -> -129948.49 | E21: ='Monthly Engine'!E60 -> -109415 | F21: ='Monthly Engine'!F60 -> -37595.406 | G21: ='Monthly Engine'!G60 -> 13425.806 | H21: ='Monthly Engine'!H60 -> -7802.8154 | I21: ='Monthly Engine'!I60 -> 51621.248 | J21: ='Monthly Engine'!J60 -> 99623.554 | ... N21: ='Monthly Engine'!N60 -> 562257.11
B22: EBITDA margin % | C22: =C21/C4 -> -0.75643905 | D22: =D21/D4 -> -0.43221887 | E22: =E21/E4 -> -0.24699101 | F22: =F21/F4 -> -0.061650609 | G22: =G21/G4 -> 0.018396456 | H22: =H21/H4 -> -0.010149948 | I22: =I21/I4 -> 0.057082324 | J22: =J21/J4 -> 0.098302365 | ... N22: =N21/N4 -> 0.26266204
B24: Capex (capacity expansion), ₹ | C24: ='Monthly Engine'!C64 -> 0 | D24: ='Monthly Engine'!D64 -> 600000 | E24: ='Monthly Engine'!E64 -> 0 | F24: ='Monthly Engine'!F64 -> 0 | G24: ='Monthly Engine'!G64 -> 0 | H24: ='Monthly Engine'!H64 -> 0 | I24: ='Monthly Engine'!I64 -> 0 | J24: ='Monthly Engine'!J64 -> 600000 | ... N24: ='Monthly Engine'!N64 -> 0
B25: Funding raise, ₹ | C25: ='Monthly Engine'!C65 -> 0 | D25: ='Monthly Engine'!D65 -> 0 | E25: ='Monthly Engine'!E65 -> 0 | F25: ='Monthly Engine'!F65 -> 0 | G25: ='Monthly Engine'!G65 -> 0 | H25: ='Monthly Engine'!H65 -> 0 | I25: ='Monthly Engine'!I65 -> 0 | J25: ='Monthly Engine'!J65 -> 0 | ... N25: ='Monthly Engine'!N65 -> 0
B26: Cash — ending, ₹ | C26: ='Monthly Engine'!C67 -> 2964301.2 | D26: ='Monthly Engine'!D67 -> 2216086.5 | E26: ='Monthly Engine'!E67 -> 2079200.3 | F26: ='Monthly Engine'!F67 -> 2003318.9 | G26: ='Monthly Engine'!G67 -> 1970832 | H26: ='Monthly Engine'!H67 -> 1914851.7 | I26: ='Monthly Engine'!I67 -> 1909840.4 | J26: ='Monthly Engine'!J67 -> 1346243.4 | ... N26: ='Monthly Engine'!N67 -> 2443479.3
B27: Covenant status (min ₹5L) | C27: ='Monthly Engine'!C68 -> ok | D27: ='Monthly Engine'!D68 -> ok | E27: ='Monthly Engine'!E68 -> ok | F27: ='Monthly Engine'!F68 -> ok | G27: ='Monthly Engine'!G68 -> ok | H27: ='Monthly Engine'!H68 -> ok | I27: ='Monthly Engine'!I68 -> ok | J27: ='Monthly Engine'!J68 -> ok | ... N27: ='Monthly Engine'!N68 -> ok
B30: Chart data (₹ lakh)
B31: Net revenue, ₹L | C31: =C4/100000 -> 2.1564105 | D31: =D4/100000 -> 3.0065436 | E31: =E4/100000 -> 4.4299186 | F31: =F4/100000 -> 6.0981402 | G31: =G4/100000 -> 7.2980394 | H31: =H4/100000 -> 7.6875426 | I31: =I4/100000 -> 9.0432983 | J31: =J4/100000 -> 10.134401 | ... N31: =N4/100000 -> 21.406104
B32: ₹1cr target line | C32: 100 | D32: 100 | E32: 100 | F32: 100 | G32: 100 | H32: 100 | I32: 100 | J32: 100 | K32: 100 | L32: 100 | M32: 100 | N32: 100

Sheet Scenario Comparison
A1: SCENARIO COMPARISON — BASE / BULL / BEAR (reference snapshot)
A2: Computed by running the live model (Monthly Engine) with the Assumptions & Log scenario switch set to each case in turn. To reproduce live, change cell B3 on 'Assumptions & Log' and re-read 'Monthly Rollup & Cash'. Values below are a point-in-time snapshot for side-by-side reading.
A4: THE 6 ASSUMPTIONS THAT DIFFER ACROSS SCENARIOS
A5: • Opening paid-spend growth (hi/lo season), Jul-26 spend | B5: Base: +16%/+5%, ₹1.15L | Bull: +21%/+9%, ₹1.35L | Bear: +7%/+1%, ₹1.00L
A6: • CAC structural drift (pre/post creative-relief) | B6: Base: 1.4%->0.5% from mo.3 | Bull: 1.2%->0.6% from mo.2 | Bear: 2.6%->0.4% from mo.6
A7: • Organic referral rate + monthly repeat probability (start->end) | B7: Base: 2.8% referral, 16%->24% repeat | Bull: 4.5% referral, 17%->30% repeat | Bear: 1.2% referral, 11%->15% repeat
A8: • Subscribe&Save: share of new custs -> sub, and renewal rate | B8: Base: 9%->24% share, 80% renewal | Bull: 10%->32%, 84% renewal | Bear: 7%->13%, 66% renewal
A9: • New-channel sequencing (Amazon / Blinkit QC) & capacity expansion | B9: Base: Amazon mo.1, QC mo.2, 2nd line mo.1 (live mo.3) | Bull: both mo.0-1, 2nd line immediate + 3rd line mo.5 | Bear: Amazon mo.2 only, no QC, no expansion
A10: • Funding raise | B10: Base: none (organic cash only) | Bull: ~₹1.8cr around Jan-27, on festive-season proof points | Bear: none
A12: EXIT SUMMARY (Jun-27)
B13: Base | C13: Bull | D13: Bear
A14: Jun-27 net revenue (MRR), ₹ | B14: 2140610.4 | C14: 4334183.4 | D14: 549281.6
A15: Growth multiple vs Jun-26 actual (₹2,51,242) | B15: 8.5201138 | C15: 17.251031 | D15: 2.186265
A16: % of ₹1cr stretch target | B16: 0.21406104 | C16: 0.43341834 | D16: 0.05492816
A17: Minimum cash during the 12 months, ₹ | B17: 1346243.4 | C17: 1841449.8 | D17: 1148818.5
A18: Jun-27 cans required | B18: 18476.45 | C18: 35393.618 | D18: 5080.2803
A19: Jun-27 capacity ceiling | B19: 144000 | C19: 144000 | D19: 48000
A22: Net revenue by month, ₹ lakh
A23: Base | B23: 2.156 | C23: 3.007 | D23: 4.43 | E23: 6.098 | F23: 7.298 | G23: 7.688 | H23: 9.043 | I23: 10.134 | J23: 12.373 | K23: 15.842 | L23: 19.011 | M23: 21.406
A24: Bull | B24: 2.644 | C24: 4.602 | D24: 7.082 | E24: 10.115 | F24: 12.449 | G24: 13.492 | H24: 16.271 | I24: 18.709 | J24: 23.292 | K24: 30.292 | L24: 37.227 | M24: 43.342
A25: Bear | B25: 1.695 | C25: 1.74 | D25: 2.117 | E25: 2.526 | F25: 2.713 | G25: 2.617 | H25: 2.873 | I25: 3.041 | J25: 3.55 | K25: 4.382 | L25: 5.079 | M25: 5.493
A26: Month | B26: Jul-26 | C26: Aug-26 | D26: Sep-26 | E26: Oct-26 | F26: Nov-26 | G26: Dec-26 | H26: Jan-27 | I26: Feb-27 | J26: Mar-27 | K26: Apr-27 | L26: May-27 | M26: Jun-27
A27: ₹1cr target | B27: 100 | C27: 100 | D27: 100 | E27: 100 | F27: 100 | G27: 100 | H27: 100 | I27: 100 | J27: 100 | K27: 100 | L27: 100 | M27: 100

Sheet Sensitivity
A1: SENSITIVITY — Jun-27 Base-case revenue to ±20% swings in each assumption
A2: Baseline Jun-27 net revenue (Base case): ₹2,140,610. Each row perturbs ONE assumption ±20% (holding all others at Base) and re-solves the live model.
A4: Assumption | B4: Revenue @ -20% | C4: Revenue @ +20% | D4: % impact (-20%) | E4: % impact (+20%)
A5: Subscription monthly renewal rate (±20%) | B5: 2041077.6 | C5: 2362480.6 | D5: -0.046497419 | E5: 0.1036481
A6: Subscribe&Save share of new custs, Jun-27 (±20%) | B6: 2076292.6 | C6: 2204928.3 | D6: -0.030046501 | E6: 0.030046501
A7: Organic referral rate off customer base (±20%) | B7: 2095635.5 | C7: 2188193.7 | D7: -0.021010338 | E7: 0.022228832
A8: Repeat-purchase probability, Jun-27 (±20%) | B8: 2100466.1 | C8: 2180754.8 | D8: -0.018753686 | E8: 0.018753686
A9: Paid-spend growth, high-season months (±20%) | B9: 2110000 | C9: 2171955.1 | D9: -0.014299846 | E9: 0.014642845
A10: Monthly AOV drift (±20%) | B10: 2115350.1 | C10: 2166426.5 | D10: -0.011800539 | E10: 0.01206014
A11: Structural CAC inflation, pre-relief (±20%) | B11: 2145785.3 | C11: 2135478.2 | D11: 0.0024174581 | E11: -0.0023975658
A13: TOP 3 — outcome is most sensitive to:
A14: 1. Subscription monthly renewal rate (±20%)
A15: 2. Subscribe&Save share of new custs, Jun-27 (±20%)
A16: 3. Organic referral rate off customer base (±20%)
A18: • Read: subscription renewal rate is by far the single biggest lever on Month-12 revenue — bigger than CAC inflation, paid-spend growth, or even the organic referral rate.
A19: • This is the model's central strategic implication: NYOD's growth ceiling is set more by whether Subscribe&Save renews (unknown — flagged in the data pack) than by paid-media efficiency.
A20: • CAC inflation, while the most visible worry in the data pack (May->Jun CAC +20%), has the smallest effect on the 12-month outcome here — because paid orders are already a shrinking share of the mix as organic/retention channels compound.
